Workbook

Sheet Start Here
B2: Software Pricing Model — Compliance Monitoring & Controls Platform
B3: Cebrion AI | Licence & Services pricing toolkit | Markets: UK / India / ME
B5: How to use this workbook
B6: You did not track build cost, so we reconstruct it. Work through the tabs in order. Only edit YELLOW cells (blue text). Everything in black is a formula — leave it alone.
B8: 1. Cost Reconstruction
B9: Rebuild your historic investment from memory: people-time, your own time, tools/cloud, and third-party costs. This gives you a defensible "total cost to build" even without invoices.
B11: 2. Cost-to-Serve
B12: Ongoing annual cost of running, supporting and maintaining the product per customer. Needed for both models — it sets your margin floor.
B14: 3. Licence Pricing
B15: Three independent methods (cost-recovery, value-based, market-anchored) plus a recommended blended licence price with tiering. Use when you sell the right to use the software.
B17: 4. Services Pricing
B18: Day-rate build-up, blended team rate, and project/managed-service pricing. Use when you sell implementation, configuration and run as a service.
... B23: Colour key: Yellow = your input | Black = calculated | Green = pulled from another tab

Sheet 1. Cost Reconstruction
B2: Cost Reconstruction — What it cost you to build
B3: Reconstruct historic investment from memory. Fill yellow cells. Effort in person-days × blended rate.
B5: A. Internal Effort (your team + your own time)
B6: Role / Workstream | C6: Person-days | D6: Day rate (£) | E6: Cost (£) | G6: Notes
B7: Solution architecture / design | C7: 25 | D7: 650 | E7: =C7*D7 -> 16250 | G7: Your design time
B8: Backend / engine development | C8: 80 | D8: 500 | E8: =C8*D8 -> 40000 | G8: Core monitoring engine
B9: Controls & rules logic | C9: 45 | D9: 500 | E9: =C9*D9 -> 22500 | G9: Compliance rule library
B10: Frontend / dashboards | C10: 40 | D10: 450 | E10: =C10*D10 -> 18000 | G10: UI build
B11: Integrations / connectors | C11: 30 | D11: 500 | E11: =C11*D11 -> 15000 | G11: Data source hookups
B12: Testing & QA | C12: 25 | D12: 400 | E12: =C12*D12 -> 10000
B13: Your own founder time (unpaid) | C13: 60 | D13: 800 | E13: =C13*D13 -> 48000 | G13: Opportunity cost of your hours
B14: Other | C14: 0 | D14: 500 | E14: =C14*D14 -> 0
B15: Subtotal — Internal effort | E15: =SUM(E7:E14) -> 169750
B17: B. Direct / Out-of-pocket Costs
B18: Item | E18: Cost (£) | G18: Notes
B19: Cloud / hosting during build (Azure) | E19: 8000 | G19: Dev & test environments
B20: Software licences & dev tools | E20: 4000 | G20: IDEs, libraries, CI/CD
B21: Third-party / contractor spend | E21: 12000 | G21: Any outsourced work
B22: Data / API subscriptions | E22: 3000
B23: Security / pen-test / audit | E23: 5000 | G23: Important for compliance product
B24: Other | E24: 0
B25: Subtotal — Direct costs | E25: =SUM(E19:E24) -> 32000
B27: C. Total Build Investment
B28: Total reconstructed build cost | E28: =E15+E25 -> 201750
B29: Contingency / uncertainty buffer (%) | E29: 0.15
B30: Adjusted total investment to recover | E30: =E28*(1+E29) -> 232012.5
B31: Target recovery period (years) | E31: 3
B32: Target required return / margin on build (%) | E32: 0.3

Sheet 2. Cost-to-Serve
B2: Cost-to-Serve — Annual cost to run & support the product
B3: Sets your margin floor. Per-customer figures drive the licence margin; total figure drives services overhead.
B5: A. Annual Run Cost (per customer, at steady state)
B6: Item | C6: Annual £ / customer | E6: Notes
B7: Cloud / hosting per customer | C7: 6000 | E7: Compute, storage, bandwidth
B8: Support & customer success (allocated) | C8: 4000 | E8: L1/L2 support time
B9: Maintenance & updates (allocated) | C9: 3500 | E9: Patches, rule updates
B10: Monitoring / security ops (allocated) | C10: 2500 | E10: SOC, compliance upkeep
B11: Account management (allocated) | C11: 2000
B12: Other | C12: 0
B13: Total cost-to-serve per customer / year | C13: =SUM(C7:C12) -> 18000
B15: B. Fixed Annual Overhead (whole product line)
B16: Item | C16: Annual £ | E16: Notes
B17: Core product engineering (roadmap) | C17: 90000 | E17: Ongoing dev, not customer-specific
B18: Compliance content / regulatory tracking | C18: 30000 | E18: Keeping rules current
B19: Sales & marketing (allocated) | C19: 40000
B20: G&A / admin (allocated) | C20: 25000
B21: Total fixed annual overhead | C21: =SUM(C17:C20) -> 185000

Sheet 3. Licence Pricing
B2: Licence Pricing — Annual subscription per customer
B3: Three methods triangulate to a recommended price. Edit yellow assumptions; pick the price you can defend.
B5: Method 1 — Cost Recovery (bottom-up floor)
B6: Adjusted build investment to recover | C6: ='1. Cost Reconstruction'!E30 -> 232012.5
B7: Recovery period (years) | C7: ='1. Cost Reconstruction'!E31 -> 3
B8: Required return / margin on build | C8: ='1. Cost Reconstruction'!E32 -> 0.3
B9: Expected paying customers over recovery period | C9: 12
B10: Annual cost-to-serve per customer | C10: ='2. Cost-to-Serve'!C13 -> 18000
B11: Build recovery per customer per year | C11: =(C6*(1+C8))/C7/C9 -> 8378.2292
B12: Licence price — cost-recovery floor | C12: =C11+C10 -> 26378.229
B14: Method 2 — Value-Based (customer ROI)
B15: Annual value delivered to customer (£) | C15: 120000
B16: Share of value you capture (%) | C16: 0.2
B17: Licence price — value-based | C17: =C15*C16 -> 24000
B19: Method 3 — Market-Anchored (competitor reference)
B20: Comparable competitor annual price (£) | C20: 60000
B21: Your positioning vs competitor (% of their price) | C21: 0.85
B22: Licence price — market-anchored | C22: =C20*C21 -> 51000
B24: Recommended Licence Price
B25: Cost-recovery floor | C25: =C12 -> 26378.229
B26: Value-based ceiling | C26: =C17 -> 24000
B27: Market reference | C27: =C22 -> 51000
B28: Weight: cost-recovery / value / market | C28: 0.25 | D28: 0.4
B29: Market weight | C29: 0.35
B30: RECOMMENDED ANNUAL LICENCE PRICE | C30: =C25*C28+C26*C28+C27*C29 -> 30444.557
B31: Gross margin at recommended price | C31: =(C30-C10)/C30 -> 0.40876132
B32: Check: price above cost-recovery floor? | C32: =IF(C30>=C25,"OK","BELOW FLOOR") -> OK
B34: Suggested Tiering (multiplier on recommended price)
B35: Tier | C35: Multiplier | D35: Annual price (£)
B36: Essentials (single entity) | C36: 0.6 | D36: =$C$30*C36 -> 18266.734
B37: Professional (multi-entity) | C37: 1 | D37: =$C$30*C37 -> 30444.557
B38: Enterprise (group + custom) | C38: 1.8 | D38: =$C$30*C38 -> 54800.203
B39: One-time implementation fee (optional) | D39: 15000

Sheet 4. Services Pricing
B2: Services Pricing — Day rates, project & managed service
B3: Build up a defensible day rate from cost, then price projects and an annual managed-service.
B5: A. Day-Rate Build-Up (per consultant)
B6: Driver | C6: Value | F6: Notes
B7: Fully-loaded annual cost of consultant (£) | C7: 95000
B8: Billable days per year | C8: 200
B9: Internal cost per day | C9: =C7/C8 -> 475
B10: Target gross margin on services (%) | C10: 0.45
B11: Calculated day rate (cost / (1-margin)) | C11: =C9/(1-C10) -> 863.63636
B13: B. Blended Team Rate
B14: Role | C14: Day rate (£) | D14: # people | E14: Day-rate weight | F14: Notes
B15: Solution architect | C15: 1100 | D15: 1 | E15: =C15*D15 -> 1100
B16: Senior consultant | C16: 900 | D16: 2 | E16: =C16*D16 -> 1800
B17: Consultant | C17: 650 | D17: 2 | E17: =C17*D17 -> 1300
B18: Analyst | C18: 450 | D18: 1 | E18: =C18*D18 -> 450
B19: Blended day rate | C19: =SUM(E15:E18)/SUM(D15:D18) -> 775
B21: C. Implementation Project Pricing
B22: Phase | C22: Days | D22: Day rate (£) | E22: Cost (£) | F22: Notes
B23: Discovery & assessment | C23: 10 | D23: =$C$19 -> 775 | E23: =C23*D23 -> 7750
B24: Configuration & setup | C24: 20 | D24: =$C$19 -> 775 | E24: =C24*D24 -> 15500
B25: Integration | C25: 15 | D25: =$C$19 -> 775 | E25: =C25*D25 -> 11625
B26: Testing & UAT | C26: 10 | D26: =$C$19 -> 775 | E26: =C26*D26 -> 7750
B27: Training & go-live | C27: 8 | D27: =$C$19 -> 775 | E27: =C27*D27 -> 6200
B28: Total project fee | D28: =SUM(D23:D27)/SUM(C23:C27) -> 61.507937 | E28: =SUM(E23:E27) -> 48825
B30: D. Annual Managed Service (run + support)
B31: Annual cost-to-serve per customer | C31: ='2. Cost-to-Serve'!C13 -> 18000
B32: Annual support days included | C32: 24
B33: Support cost (days x blended rate) | C33: =C32*C19 -> 18600
B34: Target margin on managed service (%) | C34: 0.4
B35: Annual managed-service fee | C35: =(C31+C33)/(1-C34) -> 61000

Sheet 5. Comparison
B2: Decision View — Licence vs Services (per customer, 3 years)
B3: Assumes services = one-time project + annual managed service. Licence = annual subscription.
B5: Metric | C5: Licence model | D5: Services model
B6: Year 1 revenue / customer | C6: ='3. Licence Pricing'!C30 -> 30444.557 | D6: ='4. Services Pricing'!E28+'4. Services Pricing'!C35 -> 109825
B7: Year 2 revenue / customer | C7: ='3. Licence Pricing'!C30 -> 30444.557 | D7: ='4. Services Pricing'!C35 -> 61000
B8: Year 3 revenue / customer | C8: ='3. Licence Pricing'!C30 -> 30444.557 | D8: ='4. Services Pricing'!C35 -> 61000
B9: 3-year total revenue / customer | C9: =SUM(C6:C8) -> 91333.672 | D9: =SUM(D6:D8) -> 231825
B10: 3-year cost-to-serve / customer | C10: ='2. Cost-to-Serve'!C13*3 -> 54000 | D10: ='2. Cost-to-Serve'!C13*3 -> 54000
B11: 3-year gross profit / customer | C11: =C9-C10 -> 37333.672 | D11: =D9-D10 -> 177825
B13: Scaling note
B14: Licence scales with near-zero marginal cost — best for volume/recurring ARR and a sellable asset valuation. Services scales with headcount and bills sooner — better cash early and lower customer risk, but margin is people-bound. Many firms lead with services to fund the product, then shift the same customers onto licence once proven.
