Workbook

Sheet Summary
A1: YES BANK | AI Powered Audit Intelligence System
A2: Programme Effort Estimate & Commercial Summary - Protiviti India (R&C) | M2: Ratesheet
A3: Basis: RFI ver 1.2 dated 14/08/2026 | Rates: India - R&C card @ 1 USD = INR 80.5 | Fixed Fee (Inclusive of Outlays)
A4: DOMESTIC PRICING BASIS - effort halved uniformly across every activity line (all 9 workstreams, all 207 tasks, all grades) against the initial estimate. Recovery % and contribution margin are unchanged.
A6: # | B6: Workstream | C6: Tasks | D6: Hours | E6: Person- Days | F6: Standard Fee (INR) | G6: Proposed Fee (INR) | H6: Recovery % | I6: Staff Cost (INR) | J6: Mgmt Fee 5% (INR) | K6: Direct Cost (INR) | L6: Contribution (INR) | M6: Net CM %
A7: 1 | B7: Continuous Control Monitoring (CCM) | C7: 23 | D7: ='1. CCM'!V31 -> 2499 | E7: =D7/8 -> 312.375 | F7: ='1. CCM'!$AB$5 -> 16708220 | G7: ='1. CCM'!G39 -> 6000000 | H7: =IFERROR(G7/F7,0) -> 0.35910468 | I7: ='1. CCM'!$AB$6 -> 4297200 | J7: =G7*5% -> 300000 | K7: =I7+J7 -> 4597200 | L7: =G7-K7 -> 1402800 | M7: =IFERROR(L7/G7,0) -> 0.2338
A8: 2 | B8: Pre-Audit Checks Automation | C8: 22 | D8: ='2. Pre-Audit Checks'!V30 -> 2185 | E8: =D8/8 -> 273.125 | F8: ='2. Pre-Audit Checks'!$AB$5 -> 14252160 | G8: ='2. Pre-Audit Checks'!G38 -> 5000000 | H8: =IFERROR(G8/F8,0) -> 0.35082402 | I8: ='2. Pre-Audit Checks'!$AB$6 -> 3627768 | J8: =G8*5% -> 250000 | K8: =I8+J8 -> 3877768 | L8: =G8-K8 -> 1122232 | M8: =IFERROR(L8/G8,0) -> 0.2244464
A9: 3 | B9: VKYC Audit Automation | C9: 20 | D9: ='3. VKYC Audit'!V28 -> 1625 | E9: =D9/8 -> 203.125 | F9: ='3. VKYC Audit'!$AB$5 -> 10865330 | G9: ='3. VKYC Audit'!G36 -> 4250000 | H9: =IFERROR(G9/F9,0) -> 0.39115241 | I9: ='3. VKYC Audit'!$AB$6 -> 2780592 | J9: =G9*5% -> 212500 | K9: =I9+J9 -> 2993092 | L9: =G9-K9 -> 1256908 | M9: =IFERROR(L9/G9,0) -> 0.29574306
A10: 4 | B10: KYC Audit Automation | C10: 25 | D10: ='4. KYC Audit'!V33 -> 2333 | E10: =D10/8 -> 291.625 | F10: ='4. KYC Audit'!$AB$5 -> 14999420 | G10: ='4. KYC Audit'!G41 -> 5500000 | H10: =IFERROR(G10/F10,0) -> 0.36668084 | I10: ='4. KYC Audit'!$AB$6 -> 3796320 | J10: =G10*5% -> 275000 | K10: =I10+J10 -> 4071320 | L10: =G10-K10 -> 1428680 | M10: =IFERROR(L10/G10,0) -> 0.25976
A11: 5 | B11: Audit Checklist Automation | C11: 20 | D11: ='5. Checklist Automation'!V28 -> 1287 | E11: =D11/8 -> 160.875 | F11: ='5. Checklist Automation'!$AB$5 -> 8438810 | G11: ='5. Checklist Automation'!G36 -> 3250000 | H11: =IFERROR(G11/F11,0) -> 0.38512539 | I11: ='5. Checklist Automation'!$AB$6 -> 2152848 | J11: =G11*5% -> 162500 | K11: =I11+J11 -> 2315348 | L11: =G11-K11 -> 934652 | M11: =IFERROR(L11/G11,0) -> 0.28758523
A12: 6 | B12: Data Analytics for Internal Audit (AI/ML) | C12: 26 | D12: ='6. Data Analytics'!V34 -> 2542 | E12: =D12/8 -> 317.75 | F12: ='6. Data Analytics'!$AB$5 -> 16830130 | G12: ='6. Data Analytics'!G42 -> 6750000 | H12: =IFERROR(G12/F12,0) -> 0.40106642 | I12: ='6. Data Analytics'!$AB$6 -> 4322544 | J12: =G12*5% -> 337500 | K12: =I12+J12 -> 4660044 | L12: =G12-K12 -> 2089956 | M12: =IFERROR(L12/G12,0) -> 0.30962311
A13: 7 | B13: Audit Life Cycle Management (ALCM) | C13: 23 | D13: ='7. ALCM'!V31 -> 2133 | E13: =D13/8 -> 266.625 | F13: ='7. ALCM'!$AB$5 -> 13756660 | G13: ='7. ALCM'!G39 -> 4750000 | H13: =IFERROR(G13/F13,0) -> 0.3452873 | I13: ='7. ALCM'!$AB$6 -> 3493176 | J13: =G13*5% -> 237500 | K13: =I13+J13 -> 3730676 | L13: =G13-K13 -> 1019324 | M13: =IFERROR(L13/G13,0) -> 0.21459453
A14: 8 | B14: Agentic AI for Audit Functions | C14: 28 | D14: ='8. Agentic AI'!V36 -> 3168 | E14: =D14/8 -> 396 | F14: ='8. Agentic AI'!$AB$5 -> 21105590 | G14: ='8. Agentic AI'!G44 -> 8750000 | H14: =IFERROR(G14/F14,0) -> 0.41458211 | I14: ='8. Agentic AI'!$AB$6 -> 5428344 | J14: =G14*5% -> 437500 | K14: =I14+J14 -> 5865844 | L14: =G14-K14 -> 2884156 | M14: =IFERROR(L14/G14,0) -> 0.32961783
A15: 9 | B15: ChatBot for Policies, SOPs & Document Retrieval | C15: 20 | D15: ='9. ChatBot'!V28 -> 1319 | E15: =D15/8 -> 164.875 | F15: ='9. ChatBot'!$AB$5 -> 8575590 | G15: ='9. ChatBot'!G36 -> 3250000 | H15: =IFERROR(G15/F15,0) -> 0.37898267 | I15: ='9. ChatBot'!$AB$6 -> 2198736 | J15: =G15*5% -> 162500 | K15: =I15+J15 -> 2361236 | L15: =G15-K15 -> 888764 | M15: =IFERROR(L15/G15,0) -> 0.27346585
B16: PROGRAMME TOTAL | C16: =SUM(C7:C15) -> 207 | D16: =SUM(D7:D15) -> 19091 | E16: =SUM(E7:E15) -> 2386.375 | F16: =SUM(F7:F15) -> 125531910 | G16: =SUM(G7:G15) -> 47500000 | H16: =IFERROR(G16/F16,0) -> 0.37838985 | I16: =SUM(I7:I15) -> 32097528 | J16: =SUM(J7:J15) -> 2375000 | K16: =SUM(K7:K15) -> 34472528 | L16: =SUM(L7:L15) -> 13027472 | M16: =IFERROR(L16/G16,0) -> 0.27426257
A18: TOTAL EFFORT (HOURS) | D18: PERSON-DAYS (8H) | G18: STANDARD FEE (INR) | J18: PROPOSED FEE (INR)
A19: =D16 -> 19091 | D19: =E16 -> 2386.375 | G19: =F16 -> 125531910 | J19: =G16 -> 47500000
A21: BUDGETED RECOVERY % | D21: NET CONTRIBUTION MARGIN % | G21: NET REVENUE / HOUR (INR) | J21: BLENDED COST / HOUR (INR)
A22: =H16 -> 0.37838985 | D22: =M16 -> 0.27426257 | G22: =IFERROR(G16/D16,0) -> 2488.0834 | J22: =IFERROR(I16/D16,0) -> 1681.2911
A25: PROGRAMME GRADE MIX
A26: Grade | B26: Designation | C26: Hours | D26: Mix % | E26: Cost (INR)
A27: MD | B27: Managing Director | C27: ='1. CCM'!J31+'2. Pre-Audit Checks'!J30+'3. VKYC Audit'!J28+'4. KYC Audit'!J33+'5. Checklist Automation'!J28+'6. Data Analytics'!J34+'7. ALCM'!J31+'8. Agentic AI'!J36+'9. ChatBot'!J28 -> 43 | D27: =IFERROR(C27/$C$39,0) -> 0.0022523702 | E27: =C27*Ratesheet!$F$7 -> 928800
A28: SD | B28: Senior Director | C28: ='1. CCM'!K31+'2. Pre-Audit Checks'!K30+'3. VKYC Audit'!K28+'4. KYC Audit'!K33+'5. Checklist Automation'!K28+'6. Data Analytics'!K34+'7. ALCM'!K31+'8. Agentic AI'!K36+'9. ChatBot'!K28 -> 0 | D28: =IFERROR(C28/$C$39,0) -> 0 | E28: =C28*Ratesheet!$F$8 -> 0
A29: DIR | B29: Director | C29: ='1. CCM'!L31+'2. Pre-Audit Checks'!L30+'3. VKYC Audit'!L28+'4. KYC Audit'!L33+'5. Checklist Automation'!L28+'6. Data Analytics'!L34+'7. ALCM'!L31+'8. Agentic AI'!L36+'9. ChatBot'!L28 -> 452 | D29: =IFERROR(C29/$C$39,0) -> 0.023676078 | E29: =C29*Ratesheet!$F$9 -> 4339200
A30: AD | B30: Associate Director | C30: ='1. CCM'!M31+'2. Pre-Audit Checks'!M30+'3. VKYC Audit'!M28+'4. KYC Audit'!M33+'5. Checklist Automation'!M28+'6. Data Analytics'!M34+'7. ALCM'!M31+'8. Agentic AI'!M36+'9. ChatBot'!M28 -> 1330 | D30: =IFERROR(C30/$C$39,0) -> 0.069666335 | E30: =C30*Ratesheet!$F$10 -> 7341600
A31: SR. MGR | B31: Senior Manager | C31: ='1. CCM'!N31+'2. Pre-Audit Checks'!N30+'3. VKYC Audit'!N28+'4. KYC Audit'!N33+'5. Checklist Automation'!N28+'6. Data Analytics'!N34+'7. ALCM'!N31+'8. Agentic AI'!N36+'9. ChatBot'!N28 -> 890 | D31: =IFERROR(C31/$C$39,0) -> 0.046618826 | E31: =C31*Ratesheet!$F$11 -> 3310800
A32: MGR | B32: Manager | C32: ='1. CCM'!O31+'2. Pre-Audit Checks'!O30+'3. VKYC Audit'!O28+'4. KYC Audit'!O33+'5. Checklist Automation'!O28+'6. Data Analytics'!O34+'7. ALCM'!O31+'8. Agentic AI'!O36+'9. ChatBot'!O28 -> 0 | D32: =IFERROR(C32/$C$39,0) -> 0 | E32: =C32*Ratesheet!$F$12 -> 0
A33: DM | B33: Deputy Manager | C33: ='1. CCM'!P31+'2. Pre-Audit Checks'!P30+'3. VKYC Audit'!P28+'4. KYC Audit'!P33+'5. Checklist Automation'!P28+'6. Data Analytics'!P34+'7. ALCM'!P31+'8. Agentic AI'!P36+'9. ChatBot'!P28 -> 2836 | D33: =IFERROR(C33/$C$39,0) -> 0.14855167 | E33: =C33*Ratesheet!$F$13 -> 4594320
A34: SR. CONS. | B34: Senior Consultant | C34: ='1. CCM'!Q31+'2. Pre-Audit Checks'!Q30+'3. VKYC Audit'!Q28+'4. KYC Audit'!Q33+'5. Checklist Automation'!Q28+'6. Data Analytics'!Q34+'7. ALCM'!Q31+'8. Agentic AI'!Q36+'9. ChatBot'!Q28 -> 3636 | D34: =IFERROR(C34/$C$39,0) -> 0.19045624 | E34: =C34*Ratesheet!$F$14 -> 4035960
A35: CON3 | B35: Consultant 3 | C35: ='1. CCM'!R31+'2. Pre-Audit Checks'!R30+'3. VKYC Audit'!R28+'4. KYC Audit'!R33+'5. Checklist Automation'!R28+'6. Data Analytics'!R34+'7. ALCM'!R31+'8. Agentic AI'!R36+'9. ChatBot'!R28 -> 4952 | D35: =IFERROR(C35/$C$39,0) -> 0.25938924 | E35: =C35*Ratesheet!$F$15 -> 4278528
A36: CON2 | B36: Consultant 2 | C36: ='1. CCM'!S31+'2. Pre-Audit Checks'!S30+'3. VKYC Audit'!S28+'4. KYC Audit'!S33+'5. Checklist Automation'!S28+'6. Data Analytics'!S34+'7. ALCM'!S31+'8. Agentic AI'!S36+'9. ChatBot'!S28 -> 4952 | D36: =IFERROR(C36/$C$39,0) -> 0.25938924 | E36: =C36*Ratesheet!$F$16 -> 3268320
A37: CON1 | B37: Consultant 1 | C37: ='1. CCM'!T31+'2. Pre-Audit Checks'!T30+'3. VKYC Audit'!T28+'4. KYC Audit'!T33+'5. Checklist Automation'!T28+'6. Data Analytics'!T34+'7. ALCM'!T31+'8. Agentic AI'!T36+'9. ChatBot'!T28 -> 0 | D37: =IFERROR(C37/$C$39,0) -> 0 | E37: =C37*Ratesheet!$F$17 -> 0
A38: ANLST. | B38: Analyst | C38: ='1. CCM'!U31+'2. Pre-Audit Checks'!U30+'3. VKYC Audit'!U28+'4. KYC Audit'!U33+'5. Checklist Automation'!U28+'6. Data Analytics'!U34+'7. ALCM'!U31+'8. Agentic AI'!U36+'9. ChatBot'!U28 -> 0 | D38: =IFERROR(C38/$C$39,0) -> 0 | E38: =C38*Ratesheet!$F$18 -> 0
A39: TOTAL | C39: =SUM(C27:C38) -> 19091 | D39: =SUM(D27:D38) -> 1 | E39: =SUM(E27:E38) -> 32097528
A47: BASIS OF ESTIMATE & KEY ASSUMPTIONS
A48: 0. DOMESTIC BASIS: hours on every activity line have been halved against the initial estimate, per review direction. Because Standard Fee, Staff Cost and Proposed Fee all scale with hours, Recovery % and Net CM % are unchanged. Delivery risk of the reduced effort is called out in note 13.
A49: 1. Effort is built bottom-up: each workstream is decomposed into delivery tasks and loaded by resource grade. Standard Fee = hours x India-R&C chargeout rates; Staff Cost = hours x cost rates (Ratesheet tab).
A50: 2. Proposed Fee is a commercial input (blue cells, column G / cell D on each tool sheet). Recovery % and Contribution Margin recalculate automatically. Change the fee, not the derived cells.
A51: 3. Direct Cost = standard staff cost + 5% management fee, consistent with the Protiviti project template. Outlays / OPE are budgeted at NIL - see assumption 7.
A52: 4. Delivery assumed from India (Home Office, R&C service line). No sub-contractor or other-office cost included.
A53: 5. Excludes: hardware, OS and Oracle DB licences (supplied by YES BANK per RFI 5.3); GPU infrastructure for in-perimeter LLM hosting; third-party software, middleware and tool licences; ATS / AMC beyond go-live.
A54: 6. Excludes post go-live onsite L1 & L2 support resources (RFI 3.2 item 9) - to be priced separately as a recurring annual managed-service line.
A55: 7. Outlays are NIL in this build. Travel to YES BANK House (Santacruz, Mumbai), LLM / API consumption, vector-store and OCR licences must be added to the Expenses sheet before submission, or they erode the contribution margin directly.
A56: 8. Assumes the 5,000+ concurrent-user NFR is clarified downward to Internal Audit population. If literal, add load-tier infrastructure and performance-engineering effort.
A57: 9. Assumes ALCM replaces Pentana (migration utility included). If ALCM must instead integrate with a retained Pentana, workstream 7 reduces and workstream 1 integration effort increases.
A58: 10. 'Integration' tasks are scoped at the source-system counts named in the RFI. Each additional source system beyond that list is a change request.
... A61: 13. DELIVERY RISK OF THE HALVED BASIS: the scope in the RFI is unchanged, so this estimate now assumes significant reuse of existing Protiviti accelerators (the CCM rules engine, dashboard and workflow assets already built), an agile fixed-capacity model rather than fixed-scope, and YES BANK-side ownership of data extracts, environment provisioning and UAT execution. If those three assumptions do not hold, effort reverts toward the original basis.

Sheet Ratesheet
A1: R A T E S H E E T - India / R&C
A2: Chargeout & cost rates per the Protiviti India project template (effective 1-Jul-23). All source rates in USD; INR derived at the FX rate below.
A4: FX Rate (INR per USD) | C4: 80.5 | H4: < Summary
A6: Grade | B6: Designation | C6: Chargeout USD/hr | D6: Cost USD/hr | E6: Chargeout INR/hr | F6: Cost INR/hr
A7: MD | B7: Managing Director | C7: 373.04348 | D7: 268.32298 | E7: =C7*$C$4 -> 30030 | F7: =D7*$C$4 -> 21600
A8: SD | B8: Senior Director | C8: 310.55901 | D8: 124.2236 | E8: =C8*$C$4 -> 25000 | F8: =D8*$C$4 -> 10000
A9: DIR | B9: Director | C9: 274.28571 | D9: 119.25466 | E9: =C9*$C$4 -> 22080 | F9: =D9*$C$4 -> 9600
A10: AD | B10: Associate Director | C10: 217.8882 | D10: 68.571429 | E10: =C10*$C$4 -> 17540 | F10: =D10*$C$4 -> 5520
A11: SR. MGR | B11: Senior Manager | C11: 185.21739 | D11: 46.21118 | E11: =C11*$C$4 -> 14910 | F11: =D11*$C$4 -> 3720
A12: MGR | B12: Manager | C12: 125.21739 | D12: 31.304348 | E12: =C12*$C$4 -> 10080 | F12: =D12*$C$4 -> 2520
A13: DM | B13: Deputy Manager | C13: 93.540373 | D13: 20.124224 | E13: =C13*$C$4 -> 7530 | F13: =D13*$C$4 -> 1620
A14: SR. CONS. | B14: Senior Consultant | C14: 62.608696 | D14: 13.78882 | E14: =C14*$C$4 -> 5040 | F14: =D14*$C$4 -> 1110
A15: CON3 | B15: Consultant 3 | C15: 49.440994 | D15: 10.732919 | E15: =C15*$C$4 -> 3980 | F15: =D15*$C$4 -> 864
A16: CON2 | B16: Consultant 2 | C16: 45.838509 | D16: 8.1987578 | E16: =C16*$C$4 -> 3690 | F16: =D16*$C$4 -> 660
A17: CON1 | B17: Consultant 1 | C17: 39.751553 | D17: 6.2608696 | E17: =C17*$C$4 -> 3200 | F17: =D17*$C$4 -> 504
A18: ANLST. | B18: Analyst | C18: 20.248447 | D18: 3.7267081 | E18: =C18*$C$4 -> 1630 | F18: =D18*$C$4 -> 300
A21: LOOKUP ROW (used by every tool sheet - do not reorder)
A22: Grade | B22: MD | C22: SD | D22: DIR | E22: AD | F22: SR. MGR | G22: MGR | H22: DM | I22: SR. CONS. | J22: CON3 | K22: CON2 | L22: CON1 | M22: ANLST.
A23: Chargeout INR/hr | B23: =$E$7 -> 30030 | C23: =$E$8 -> 25000 | D23: =$E$9 -> 22080 | E23: =$E$10 -> 17540 | F23: =$E$11 -> 14910 | G23: =$E$12 -> 10080 | H23: =$E$13 -> 7530 | I23: =$E$14 -> 5040 | J23: =$E$15 -> 3980 | K23: =$E$16 -> 3690 | L23: =$E$17 -> 3200 | M23: =$E$18 -> 1630
A24: Cost INR/hr | B24: =$F$7 -> 21600 | C24: =$F$8 -> 10000 | D24: =$F$9 -> 9600 | E24: =$F$10 -> 5520 | F24: =$F$11 -> 3720 | G24: =$F$12 -> 2520 | H24: =$F$13 -> 1620 | I24: =$F$14 -> 1110 | J24: =$F$15 -> 864 | K24: =$F$16 -> 660 | L24: =$F$17 -> 504 | M24: =$F$18 -> 300

Sheet 1. CCM
A1: Protiviti Member Firm (India) | V1: Project Template 2023 Apr.23
A2: Project Template - Fixed Fee Inclusive Outlays
A4: Organisation: | C4: India - R&C | X4: < Summary | Z4: RATE ENGINE (auto)
A5: Client Legal Name: | C5: YES BANK Ltd. | F5: Resource Plan (Home Office) - Budgeted Hours by Task and Resource Category | Z5: Standard Revenue (INR) | AB5: =SUMPRODUCT(J31:U31,Ratesheet!$B$23:$M$23) -> 16708220
A6: Project Description: | C6: Continuous Control Monitoring (CCM) | F6: Task Name | H6: Business Unit | J6: MD | K6: SD | L6: DIR | M6: AD | N6: SR. MGR | O6: MGR | P6: DM | Q6: SR. CONS. | R6: CON3 | S6: CON2 | T6: CON1 | U6: ANLST. | V6: TOTAL | X6: Ratesheet | Z6: Standard Staff Cost (INR) | AB6: =SUMPRODUCT(J31:U31,Ratesheet!$B$24:$M$24) -> 4297200
A7: Billing Currency: | C7: INR | H7: Country | I7: Service line | Z7: Blended chargeout / hr | AB7: =IFERROR(AB5/V31,0) -> 6685.9624
A8: Project Type: | C8: Fixed Fee (Incl. Outlays) | F8: Requirement Gathering, Control Universe & Feasibility Study | H8: India | I8: R&C | J8: 2 | L8: 12 | M8: 12 | P8: 20 | Q8: 20 | R8: 24 | S8: 24 | V8: =SUM(J8:U8) -> 114 | Z8: Blended cost / hr | AB8: =IFERROR(AB6/V31,0) -> 1719.5678
F9: Technical Architecture, Design & Planning | H9: India | I9: R&C | J9: 2 | L9: 16 | M9: 16 | P9: 20 | Q9: 20 | R9: 20 | S9: 20 | V9: =SUM(J9:U9) -> 114
F10: Data Model & Database Design | H10: India | I10: R&C | J10: 1 | L10: 6 | M10: 8 | P10: 16 | Q10: 16 | R10: 24 | S10: 24 | V10: =SUM(J10:U10) -> 95
F11: Data Warehouse & Source System Ingestion Framework | H11: India | I11: R&C | L11: 4 | M11: 12 | P11: 24 | Q11: 32 | R11: 48 | S11: 48 | V11: =SUM(J11:U11) -> 168
F12: Control Rule Engine & Rule Library Build | H12: India | I12: R&C | L12: 6 | M12: 16 | P12: 28 | Q12: 36 | R12: 56 | S12: 56 | V12: =SUM(J12:U12) -> 198
F13: No-Code Rule & Threshold Configurator | H13: India | I13: R&C | L13: 2 | M13: 8 | P13: 20 | Q13: 24 | R13: 36 | S13: 36 | V13: =SUM(J13:U13) -> 126
F14: Exception Management, Risk Scoring & Alerting Engine | H14: India | I14: R&C | L14: 2 | M14: 10 | P14: 24 | Q14: 32 | R14: 44 | S14: 44 | V14: =SUM(J14:U14) -> 156
F15: Remediation Workflow & Auditee Assignment | H15: India | I15: R&C | M15: 6 | P15: 16 | Q15: 20 | R15: 28 | S15: 28 | V15: =SUM(J15:U15) -> 98
F16: Correlation, Root-Cause & Trend Analytics | H16: India | I16: R&C | L16: 2 | M16: 8 | P16: 16 | Q16: 20 | R16: 28 | S16: 28 | V16: =SUM(J16:U16) -> 102
F17: Change & Configuration Drift Detection | H17: India | I17: R&C | M17: 4 | P17: 12 | Q17: 16 | R17: 20 | S17: 20 | V17: =SUM(J17:U17) -> 72
F18: Orchestration & Automated Response Hooks | H18: India | I18: R&C | M18: 4 | P18: 12 | Q18: 16 | R18: 20 | S18: 20 | V18: =SUM(J18:U18) -> 72
F19: API Layer & Microservices Implementation | H19: India | I19: R&C | L19: 4 | M19: 8 | P19: 20 | Q19: 24 | R19: 40 | S19: 40 | V19: =SUM(J19:U19) -> 136
F20: Frontend Design & Real-Time Control Dashboards | H20: India | I20: R&C | M20: 8 | P20: 24 | Q20: 32 | R20: 48 | S20: 48 | V20: =SUM(J20:U20) -> 160
F21: FE & BE Integration | H21: India | I21: R&C | M21: 6 | P21: 16 | Q21: 24 | R21: 28 | S21: 28 | V21: =SUM(J21:U21) -> 102
F22: Regulatory Evidence & ACB Report Generation | H22: India | I22: R&C | L22: 2 | M22: 4 | P22: 12 | Q22: 16 | R22: 20 | S22: 20 | V22: =SUM(J22:U22) -> 74
F23: Audit Management Application (Pentana) Integration | H23: India | I23: R&C | L23: 2 | M23: 4 | P23: 12 | Q23: 16 | R23: 20 | S23: 20 | V23: =SUM(J23:U23) -> 74
F24: Auth, RBAC, NFR & Security Implementation | H24: India | I24: R&C | M24: 8 | P24: 16 | Q24: 20 | R24: 24 | S24: 24 | V24: =SUM(J24:U24) -> 92
F25: Component Testing & SIT | H25: India | I25: R&C | L25: 2 | M25: 8 | P25: 20 | Q25: 28 | R25: 36 | S25: 36 | V25: =SUM(J25:U25) -> 130
F26: User Acceptance Testing (incl. Bug Fixing) | H26: India | I26: R&C | L26: 1 | M26: 6 | P26: 12 | Q26: 20 | R26: 28 | S26: 28 | V26: =SUM(J26:U26) -> 95
F27: Documentation (Technical, User, DR/BCP) | H27: India | I27: R&C | M27: 4 | P27: 12 | Q27: 16 | R27: 20 | S27: 20 | V27: =SUM(J27:U27) -> 72
F28: PMO & Programme Governance | H28: India | I28: R&C | N28: 140 | V28: =SUM(J28:U28) -> 140
F29: Go-live & Hypercare Support | H29: India | I29: R&C | M29: 4 | P29: 8 | Q29: 12 | R29: 16 | S29: 16 | V29: =SUM(J29:U29) -> 56
F30: Handover & Knowledge Transfer | H30: India | I30: R&C | J30: 1 | L30: 4 | M30: 4 | P30: 8 | Q30: 12 | R30: 12 | S30: 12 | V30: =SUM(J30:U30) -> 53
F31: Total | J31: =SUM(J8:J30) -> 6 | K31: =SUM(K8:K30) -> 0 | L31: =SUM(L8:L30) -> 65 | M31: =SUM(M8:M30) -> 168 | N31: =SUM(N8:N30) -> 140 | O31: =SUM(O8:O30) -> 0 | P31: =SUM(P8:P30) -> 368 | Q31: =SUM(Q8:Q30) -> 472 | ... V31: =SUM(V8:V30) -> 2499
H33: Project Mix | J33: =IFERROR(J31/$V$31,0) -> 0.0024009604 | K33: =IFERROR(K31/$V$31,0) -> 0 | L33: =IFERROR(L31/$V$31,0) -> 0.026010404 | M33: =IFERROR(M31/$V$31,0) -> 0.067226891 | N33: =IFERROR(N31/$V$31,0) -> 0.056022409 | O33: =IFERROR(O31/$V$31,0) -> 0 | P33: =IFERROR(P31/$V$31,0) -> 0.1472589 | Q33: =IFERROR(Q31/$V$31,0) -> 0.18887555 | ... U33: =IFERROR(U31/$V$31,0) -> 0
A36: F E E B R E A K D O W N | H36: =" All Values in ( "&C7&" )" -> All Values in ( INR ) | L36: What if analysis - FYI Only
A37: Total Engagement Value | D37: 6000000 | E37: Expenses Budgeting | L37: Pricing Tool - Home Office | Q37: Fee Amount | S37: Recovery %
A38: Description | D38: Org./ Name | F38: Hours Breakdown | G38: Fee Breakdown | H38: Budgeted Outlays | L38: Standard Fee | Q38: =$AB$5 -> 16708220 | S38: =$AB$5 -> 16708220
A39: Home Office | D39: =C4 -> India - R&C | F39: =V31 -> 2499 | G39: =D37-(SUM(G40:G43)+H44) -> 6000000 | H39: 0 | L39: ="Proposed Fee (Home Office)"&" - "&IF(D39=0,"",D39) -> Proposed Fee (Home Office) - India - R&C | Q39: =G39 -> 6000000 | S39: =S38*S42 -> 6000000
A40: Sub-Contractor (3rd party) | F40: 0 | G40: 0 | H40: 0 | L40: Planned Fee Adjustment (PFA) | Q40: =Q38-Q39 -> 10708220 | S40: =S38-S39 -> 10708220
F41: 0 | G41: 0 | H41: 0 | L41: PFA % | Q41: =IFERROR(Q40/Q38,0) -> 0.64089532 | S41: =1-S42 -> 0.64089532
F42: 0 | G42: 0 | H42: 0 | L42: Recovery % | Q42: =1-Q41 -> 0.35910468 | S42: =F46 -> 0.35910468
A43: GST | F43: 0 | G43: 0 | H43: 0
A44: Total | F44: =SUM(F39:F43) -> 2499 | G44: =SUM(G39:G43) -> 6000000 | H44: =SUM(H39:H43) -> 0
C46: Budgeted Recovery % | F46: =IFERROR(G39/$AB$5,0) -> 0.35910468
L47: Gross Fee | N47: Net Fee | P47: Net CM | R47: Gross CM
L48: Fee | M48: Per/Hr | N48: Fee | O48: Per/Hr | P48: % | R48: % | T48: Margin | V48: Staff Cost
K49: =C7 -> INR | L49: =G44 -> 6000000 | M49: =IFERROR(L49/F44,0) -> 2400.9604 | N49: =G39 -> 6000000 | O49: =IFERROR(N49/V31,0) -> 2400.9604 | P49: =IFERROR((T49-(N49*5%))/N49,0) -> 0.2338 | R49: =IFERROR((L49-V49-(G44-G39)-(N49*5%))/L49,0) -> 0.2338 | T49: =IFERROR(N49-V49,0) -> 1702800 | V49: =IFERROR($AB$6,0) -> 4297200
D51: Data to be entered / editable | L51: Gross Contribution Margin is derived after considering direct staff cost, management fees, Sub-contractor cost and other direct cost. Net Contribution Margin is derived after considering direct staff cost, management fees and other direct cost.
D52: Calculated - do not overwrite

Sheet 2. Pre-Audit Checks
A1: Protiviti Member Firm (India) | V1: Project Template 2023 Apr.23
A2: Project Template - Fixed Fee Inclusive Outlays
A4: Organisation: | C4: India - R&C | X4: < Summary | Z4: RATE ENGINE (auto)
A5: Client Legal Name: | C5: YES BANK Ltd. | F5: Resource Plan (Home Office) - Budgeted Hours by Task and Resource Category | Z5: Standard Revenue (INR) | AB5: =SUMPRODUCT(J30:U30,Ratesheet!$B$23:$M$23) -> 14252160
A6: Project Description: | C6: Pre-Audit Checks Automation | F6: Task Name | H6: Business Unit | J6: MD | K6: SD | L6: DIR | M6: AD | N6: SR. MGR | O6: MGR | P6: DM | Q6: SR. CONS. | R6: CON3 | S6: CON2 | T6: CON1 | U6: ANLST. | V6: TOTAL | X6: Ratesheet | Z6: Standard Staff Cost (INR) | AB6: =SUMPRODUCT(J30:U30,Ratesheet!$B$24:$M$24) -> 3627768
A7: Billing Currency: | C7: INR | H7: Country | I7: Service line | Z7: Blended chargeout / hr | AB7: =IFERROR(AB5/V30,0) -> 6522.7277
A8: Project Type: | C8: Fixed Fee (Incl. Outlays) | F8: Requirement Gathering & Audit Programme Study | H8: India | I8: R&C | J8: 2 | L8: 10 | M8: 10 | P8: 16 | Q8: 16 | R8: 20 | S8: 20 | V8: =SUM(J8:U8) -> 94 | Z8: Blended cost / hr | AB8: =IFERROR(AB6/V30,0) -> 1660.3057
F9: Technical Architecture, Design & Planning | H9: India | I9: R&C | J9: 2 | L9: 12 | M9: 12 | P9: 16 | Q9: 16 | R9: 16 | S9: 16 | V9: =SUM(J9:U9) -> 90
F10: Data Model & Database Design | H10: India | I10: R&C | J10: 1 | L10: 4 | M10: 6 | P10: 12 | Q10: 16 | R10: 20 | S10: 20 | V10: =SUM(J10:U10) -> 79
F11: Multi-System Ingestion (CBS, LOS, LMS, GL, HRMS, CRM) | H11: India | I11: R&C | L11: 4 | M11: 12 | P11: 28 | Q11: 36 | R11: 56 | S11: 56 | V11: =SUM(J11:U11) -> 192
F12: File-Based Ingestion & Automated Schema Validation | H12: India | I12: R&C | M12: 4 | P12: 12 | Q12: 16 | R12: 24 | S12: 24 | V12: =SUM(J12:U12) -> 80
F13: Pre-Audit Validation Rule Library (5 control domains) | H13: India | I13: R&C | L13: 4 | M13: 12 | P13: 24 | Q13: 32 | R13: 48 | S13: 48 | V13: =SUM(J13:U13) -> 168
F14: Custom Rule Builder & What-If Simulation | H14: India | I14: R&C | L14: 2 | M14: 8 | P14: 20 | Q14: 24 | R14: 36 | S14: 36 | V14: =SUM(J14:U14) -> 126
F15: Automated Sampling Engine (risk/random/stratified) | H15: India | I15: R&C | L15: 2 | M15: 8 | P15: 16 | Q15: 20 | R15: 32 | S15: 32 | V15: =SUM(J15:U15) -> 110
F16: Dynamic Checklist Generation & Auto-Population | H16: India | I16: R&C | M16: 6 | P16: 16 | Q16: 20 | R16: 28 | S16: 28 | V16: =SUM(J16:U16) -> 98
F17: Exception Reporting, Severity Tagging & Risk Flags | H17: India | I17: R&C | M17: 6 | P17: 16 | Q17: 20 | R17: 28 | S17: 28 | V17: =SUM(J17:U17) -> 98
F18: API Layer & Microservices Implementation | H18: India | I18: R&C | L18: 2 | M18: 6 | P18: 16 | Q18: 20 | R18: 32 | S18: 32 | V18: =SUM(J18:U18) -> 108
F19: Frontend Design & Audit Readiness Dashboards | H19: India | I19: R&C | M19: 8 | P19: 20 | Q19: 28 | R19: 40 | S19: 40 | V19: =SUM(J19:U19) -> 136
F20: FE & BE Integration | H20: India | I20: R&C | M20: 6 | P20: 16 | Q20: 20 | R20: 24 | S20: 24 | V20: =SUM(J20:U20) -> 90
F21: Workflow, Query Management & Collaboration | H21: India | I21: R&C | M21: 6 | P21: 16 | Q21: 20 | R21: 28 | S21: 28 | V21: =SUM(J21:U21) -> 98
F22: Reporting & Export Engine (PDF / Excel / Word) | H22: India | I22: R&C | M22: 4 | P22: 12 | Q22: 16 | R22: 20 | S22: 20 | V22: =SUM(J22:U22) -> 72
F23: Auth, RBAC, Audit Trail & NFR Implementation | H23: India | I23: R&C | M23: 6 | P23: 16 | Q23: 20 | R23: 24 | S23: 24 | V23: =SUM(J23:U23) -> 90
F24: Component Testing & SIT | H24: India | I24: R&C | L24: 2 | M24: 6 | P24: 16 | Q24: 24 | R24: 32 | S24: 32 | V24: =SUM(J24:U24) -> 112
F25: User Acceptance Testing (incl. Bug Fixing) | H25: India | I25: R&C | L25: 1 | M25: 4 | P25: 12 | Q25: 16 | R25: 24 | S25: 24 | V25: =SUM(J25:U25) -> 81
F26: Documentation (Technical, User, DR/BCP) | H26: India | I26: R&C | M26: 4 | P26: 8 | Q26: 12 | R26: 16 | S26: 16 | V26: =SUM(J26:U26) -> 56
F27: PMO & Programme Governance | H27: India | I27: R&C | N27: 110 | V27: =SUM(J27:U27) -> 110
F28: Go-live & Hypercare Support | H28: India | I28: R&C | M28: 4 | P28: 8 | Q28: 12 | R28: 12 | S28: 12 | V28: =SUM(J28:U28) -> 48
F29: Handover & Knowledge Transfer | H29: India | I29: R&C | J29: 1 | L29: 4 | M29: 4 | P29: 8 | Q29: 8 | R29: 12 | S29: 12 | V29: =SUM(J29:U29) -> 49
F30: Total | J30: =SUM(J8:J29) -> 6 | K30: =SUM(K8:K29) -> 0 | L30: =SUM(L8:L29) -> 47 | M30: =SUM(M8:M29) -> 142 | N30: =SUM(N8:N29) -> 110 | O30: =SUM(O8:O29) -> 0 | P30: =SUM(P8:P29) -> 324 | Q30: =SUM(Q8:Q29) -> 412 | ... V30: =SUM(V8:V29) -> 2185
H32: Project Mix | J32: =IFERROR(J30/$V$30,0) -> 0.0027459954 | K32: =IFERROR(K30/$V$30,0) -> 0 | L32: =IFERROR(L30/$V$30,0) -> 0.021510297 | M32: =IFERROR(M30/$V$30,0) -> 0.064988558 | N32: =IFERROR(N30/$V$30,0) -> 0.050343249 | O32: =IFERROR(O30/$V$30,0) -> 0 | P32: =IFERROR(P30/$V$30,0) -> 0.14828375 | Q32: =IFERROR(Q30/$V$30,0) -> 0.18855835 | ... U32: =IFERROR(U30/$V$30,0) -> 0
A35: F E E B R E A K D O W N | H35: =" All Values in ( "&C7&" )" -> All Values in ( INR ) | L35: What if analysis - FYI Only
A36: Total Engagement Value | D36: 5000000 | E36: Expenses Budgeting | L36: Pricing Tool - Home Office | Q36: Fee Amount | S36: Recovery %
A37: Description | D37: Org./ Name | F37: Hours Breakdown | G37: Fee Breakdown | H37: Budgeted Outlays | L37: Standard Fee | Q37: =$AB$5 -> 14252160 | S37: =$AB$5 -> 14252160
A38: Home Office | D38: =C4 -> India - R&C | F38: =V30 -> 2185 | G38: =D36-(SUM(G39:G42)+H43) -> 5000000 | H38: 0 | L38: ="Proposed Fee (Home Office)"&" - "&IF(D38=0,"",D38) -> Proposed Fee (Home Office) - India - R&C | Q38: =G38 -> 5000000 | S38: =S37*S41 -> 5000000
A39: Sub-Contractor (3rd party) | F39: 0 | G39: 0 | H39: 0 | L39: Planned Fee Adjustment (PFA) | Q39: =Q37-Q38 -> 9252160 | S39: =S37-S38 -> 9252160
F40: 0 | G40: 0 | H40: 0 | L40: PFA % | Q40: =IFERROR(Q39/Q37,0) -> 0.64917598 | S40: =1-S41 -> 0.64917598
F41: 0 | G41: 0 | H41: 0 | L41: Recovery % | Q41: =1-Q40 -> 0.35082402 | S41: =F45 -> 0.35082402
A42: GST | F42: 0 | G42: 0 | H42: 0
A43: Total | F43: =SUM(F38:F42) -> 2185 | G43: =SUM(G38:G42) -> 5000000 | H43: =SUM(H38:H42) -> 0
C45: Budgeted Recovery % | F45: =IFERROR(G38/$AB$5,0) -> 0.35082402
L46: Gross Fee | N46: Net Fee | P46: Net CM | R46: Gross CM
L47: Fee | M47: Per/Hr | N47: Fee | O47: Per/Hr | P47: % | R47: % | T47: Margin | V47: Staff Cost
K48: =C7 -> INR | L48: =G43 -> 5000000 | M48: =IFERROR(L48/F43,0) -> 2288.3295 | N48: =G38 -> 5000000 | O48: =IFERROR(N48/V30,0) -> 2288.3295 | P48: =IFERROR((T48-(N48*5%))/N48,0) -> 0.2244464 | R48: =IFERROR((L48-V48-(G43-G38)-(N48*5%))/L48,0) -> 0.2244464 | T48: =IFERROR(N48-V48,0) -> 1372232 | V48: =IFERROR($AB$6,0) -> 3627768
D50: Data to be entered / editable | L50: Gross Contribution Margin is derived after considering direct staff cost, management fees, Sub-contractor cost and other direct cost. Net Contribution Margin is derived after considering direct staff cost, management fees and other direct cost.
D51: Calculated - do not overwrite

Sheet 3. VKYC Audit
A1: Protiviti Member Firm (India) | V1: Project Template 2023 Apr.23
A2: Project Template - Fixed Fee Inclusive Outlays
A4: Organisation: | C4: India - R&C | X4: < Summary | Z4: RATE ENGINE (auto)
A5: Client Legal Name: | C5: YES BANK Ltd. | F5: Resource Plan (Home Office) - Budgeted Hours by Task and Resource Category | Z5: Standard Revenue (INR) | AB5: =SUMPRODUCT(J28:U28,Ratesheet!$B$23:$M$23) -> 10865330
A6: Project Description: | C6: VKYC Audit Automation | F6: Task Name | H6: Business Unit | J6: MD | K6: SD | L6: DIR | M6: AD | N6: SR. MGR | O6: MGR | P6: DM | Q6: SR. CONS. | R6: CON3 | S6: CON2 | T6: CON1 | U6: ANLST. | V6: TOTAL | X6: Ratesheet | Z6: Standard Staff Cost (INR) | AB6: =SUMPRODUCT(J28:U28,Ratesheet!$B$24:$M$24) -> 2780592
A7: Billing Currency: | C7: INR | H7: Country | I7: Service line | Z7: Blended chargeout / hr | AB7: =IFERROR(AB5/V28,0) -> 6686.3569
A8: Project Type: | C8: Fixed Fee (Incl. Outlays) | F8: Requirement Gathering & VKYC Process Study | H8: India | I8: R&C | J8: 1 | L8: 8 | M8: 8 | P8: 12 | Q8: 12 | R8: 16 | S8: 16 | V8: =SUM(J8:U8) -> 73 | Z8: Blended cost / hr | AB8: =IFERROR(AB6/V28,0) -> 1711.1335
F9: Technical Architecture, Design & Planning | H9: India | I9: R&C | J9: 1 | L9: 8 | M9: 8 | P9: 12 | Q9: 12 | R9: 12 | S9: 12 | V9: =SUM(J9:U9) -> 65
F10: Data Model & Media Store Design | H10: India | I10: R&C | L10: 4 | M10: 6 | P10: 12 | Q10: 12 | R10: 16 | S10: 16 | V10: =SUM(J10:U10) -> 66
F11: VKYC Artefact Ingestion (video, audio, form data) | H11: India | I11: R&C | L11: 2 | M11: 8 | P11: 20 | Q11: 24 | R11: 36 | S11: 36 | V11: =SUM(J11:U11) -> 126
F12: Speech-to-Text & Audio Analytics Pipeline | H12: India | I12: R&C | L12: 4 | M12: 12 | P12: 24 | Q12: 28 | R12: 36 | S12: 36 | V12: =SUM(J12:U12) -> 140
F13: Cognitive Text & NLP Analytics on Transcripts | H13: India | I13: R&C | L13: 4 | M13: 12 | P13: 20 | Q13: 24 | R13: 32 | S13: 32 | V13: =SUM(J13:U13) -> 124
F14: Face Match / Liveness Evidence Validation | H14: India | I14: R&C | L14: 2 | M14: 8 | P14: 16 | Q14: 20 | R14: 28 | S14: 28 | V14: =SUM(J14:U14) -> 102
F15: Rule-Driven VKYC Compliance Evaluation Engine | H15: India | I15: R&C | L15: 2 | M15: 8 | P15: 16 | Q15: 20 | R15: 28 | S15: 28 | V15: =SUM(J15:U15) -> 102
F16: Exception Detection, Evidencing & Audit Trail | H16: India | I16: R&C | M16: 4 | P16: 12 | Q16: 16 | R16: 20 | S16: 20 | V16: =SUM(J16:U16) -> 72
F17: API Layer & VKYC Repository Integration | H17: India | I17: R&C | M17: 4 | P17: 12 | Q17: 16 | R17: 24 | S17: 24 | V17: =SUM(J17:U17) -> 80
F18: Frontend Design & Reviewer Console | H18: India | I18: R&C | M18: 6 | P18: 16 | Q18: 20 | R18: 28 | S18: 28 | V18: =SUM(J18:U18) -> 98
F19: FE & BE Integration | H19: India | I19: R&C | M19: 4 | P19: 12 | Q19: 16 | R19: 20 | S19: 20 | V19: =SUM(J19:U19) -> 72
F20: Model Validation, Accuracy Tuning & Bias Testing | H20: India | I20: R&C | L20: 2 | M20: 8 | P20: 16 | Q20: 20 | R20: 20 | S20: 20 | V20: =SUM(J20:U20) -> 86
F21: Auth, RBAC, Audit Trail & NFR Implementation | H21: India | I21: R&C | M21: 4 | P21: 12 | Q21: 16 | R21: 20 | S21: 20 | V21: =SUM(J21:U21) -> 72
F22: Component Testing & SIT | H22: India | I22: R&C | L22: 1 | M22: 4 | P22: 12 | Q22: 16 | R22: 24 | S22: 24 | V22: =SUM(J22:U22) -> 81
F23: User Acceptance Testing (incl. Bug Fixing) | H23: India | I23: R&C | L23: 1 | M23: 4 | P23: 8 | Q23: 12 | R23: 16 | S23: 16 | V23: =SUM(J23:U23) -> 57
F24: Documentation (Technical, User, Model Card) | H24: India | I24: R&C | M24: 4 | P24: 8 | Q24: 12 | R24: 12 | S24: 12 | V24: =SUM(J24:U24) -> 48
F25: PMO & Programme Governance | H25: India | I25: R&C | N25: 80 | V25: =SUM(J25:U25) -> 80
F26: Go-live & Hypercare Support | H26: India | I26: R&C | M26: 2 | P26: 8 | Q26: 8 | R26: 12 | S26: 12 | V26: =SUM(J26:U26) -> 42
F27: Handover & Knowledge Transfer | H27: India | I27: R&C | J27: 1 | L27: 2 | M27: 4 | P27: 8 | Q27: 8 | R27: 8 | S27: 8 | V27: =SUM(J27:U27) -> 39
F28: Total | J28: =SUM(J8:J27) -> 3 | K28: =SUM(K8:K27) -> 0 | L28: =SUM(L8:L27) -> 40 | M28: =SUM(M8:M27) -> 118 | N28: =SUM(N8:N27) -> 80 | O28: =SUM(O8:O27) -> 0 | P28: =SUM(P8:P27) -> 256 | Q28: =SUM(Q8:Q27) -> 312 | ... V28: =SUM(V8:V27) -> 1625
H30: Project Mix | J30: =IFERROR(J28/$V$28,0) -> 0.0018461538 | K30: =IFERROR(K28/$V$28,0) -> 0 | L30: =IFERROR(L28/$V$28,0) -> 0.024615385 | M30: =IFERROR(M28/$V$28,0) -> 0.072615385 | N30: =IFERROR(N28/$V$28,0) -> 0.049230769 | O30: =IFERROR(O28/$V$28,0) -> 0 | P30: =IFERROR(P28/$V$28,0) -> 0.15753846 | Q30: =IFERROR(Q28/$V$28,0) -> 0.192 | ... U30: =IFERROR(U28/$V$28,0) -> 0
A33: F E E B R E A K D O W N | H33: =" All Values in ( "&C7&" )" -> All Values in ( INR ) | L33: What if analysis - FYI Only
A34: Total Engagement Value | D34: 4250000 | E34: Expenses Budgeting | L34: Pricing Tool - Home Office | Q34: Fee Amount | S34: Recovery %
A35: Description | D35: Org./ Name | F35: Hours Breakdown | G35: Fee Breakdown | H35: Budgeted Outlays | L35: Standard Fee | Q35: =$AB$5 -> 10865330 | S35: =$AB$5 -> 10865330
A36: Home Office | D36: =C4 -> India - R&C | F36: =V28 -> 1625 | G36: =D34-(SUM(G37:G40)+H41) -> 4250000 | H36: 0 | L36: ="Proposed Fee (Home Office)"&" - "&IF(D36=0,"",D36) -> Proposed Fee (Home Office) - India - R&C | Q36: =G36 -> 4250000 | S36: =S35*S39 -> 4250000
A37: Sub-Contractor (3rd party) | F37: 0 | G37: 0 | H37: 0 | L37: Planned Fee Adjustment (PFA) | Q37: =Q35-Q36 -> 6615330 | S37: =S35-S36 -> 6615330
F38: 0 | G38: 0 | H38: 0 | L38: PFA % | Q38: =IFERROR(Q37/Q35,0) -> 0.60884759 | S38: =1-S39 -> 0.60884759
F39: 0 | G39: 0 | H39: 0 | L39: Recovery % | Q39: =1-Q38 -> 0.39115241 | S39: =F43 -> 0.39115241
A40: GST | F40: 0 | G40: 0 | H40: 0
A41: Total | F41: =SUM(F36:F40) -> 1625 | G41: =SUM(G36:G40) -> 4250000 | H41: =SUM(H36:H40) -> 0
C43: Budgeted Recovery % | F43: =IFERROR(G36/$AB$5,0) -> 0.39115241
L44: Gross Fee | N44: Net Fee | P44: Net CM | R44: Gross CM
L45: Fee | M45: Per/Hr | N45: Fee | O45: Per/Hr | P45: % | R45: % | T45: Margin | V45: Staff Cost
K46: =C7 -> INR | L46: =G41 -> 4250000 | M46: =IFERROR(L46/F41,0) -> 2615.3846 | N46: =G36 -> 4250000 | O46: =IFERROR(N46/V28,0) -> 2615.3846 | P46: =IFERROR((T46-(N46*5%))/N46,0) -> 0.29574306 | R46: =IFERROR((L46-V46-(G41-G36)-(N46*5%))/L46,0) -> 0.29574306 | T46: =IFERROR(N46-V46,0) -> 1469408 | V46: =IFERROR($AB$6,0) -> 2780592
D48: Data to be entered / editable | L48: Gross Contribution Margin is derived after considering direct staff cost, management fees, Sub-contractor cost and other direct cost. Net Contribution Margin is derived after considering direct staff cost, management fees and other direct cost.
D49: Calculated - do not overwrite

Sheet 4. KYC Audit
A1: Protiviti Member Firm (India) | V1: Project Template 2023 Apr.23
A2: Project Template - Fixed Fee Inclusive Outlays
A4: Organisation: | C4: India - R&C | X4: < Summary | Z4: RATE ENGINE (auto)
A5: Client Legal Name: | C5: YES BANK Ltd. | F5: Resource Plan (Home Office) - Budgeted Hours by Task and Resource Category | Z5: Standard Revenue (INR) | AB5: =SUMPRODUCT(J33:U33,Ratesheet!$B$23:$M$23) -> 14999420
A6: Project Description: | C6: KYC Audit Automation | F6: Task Name | H6: Business Unit | J6: MD | K6: SD | L6: DIR | M6: AD | N6: SR. MGR | O6: MGR | P6: DM | Q6: SR. CONS. | R6: CON3 | S6: CON2 | T6: CON1 | U6: ANLST. | V6: TOTAL | X6: Ratesheet | Z6: Standard Staff Cost (INR) | AB6: =SUMPRODUCT(J33:U33,Ratesheet!$B$24:$M$24) -> 3796320
A7: Billing Currency: | C7: INR | H7: Country | I7: Service line | Z7: Blended chargeout / hr | AB7: =IFERROR(AB5/V33,0) -> 6429.2413
A8: Project Type: | C8: Fixed Fee (Incl. Outlays) | F8: Requirement Gathering & RBI KYC Master Direction Study | H8: India | I8: R&C | J8: 2 | L8: 10 | M8: 10 | P8: 16 | Q8: 16 | R8: 20 | S8: 20 | V8: =SUM(J8:U8) -> 94 | Z8: Blended cost / hr | AB8: =IFERROR(AB6/V33,0) -> 1627.2267
F9: Technical Architecture, Design & Planning | H9: India | I9: R&C | J9: 2 | L9: 10 | M9: 10 | P9: 12 | Q9: 12 | R9: 16 | S9: 16 | V9: =SUM(J9:U9) -> 78
F10: Data Model & Database Design | H10: India | I10: R&C | J10: 1 | L10: 4 | M10: 6 | P10: 12 | Q10: 16 | R10: 20 | S10: 20 | V10: =SUM(J10:U10) -> 79
F11: KYC Data Ingestion (CBS, CRM, CIF, AML, LOS, DMS) | H11: India | I11: R&C | L11: 4 | M11: 12 | P11: 24 | Q11: 32 | R11: 48 | S11: 48 | V11: =SUM(J11:U11) -> 168
F12: OCR / Intelligent Document Processing Pipeline | H12: India | I12: R&C | L12: 4 | M12: 12 | P12: 24 | Q12: 28 | R12: 44 | S12: 44 | V12: =SUM(J12:U12) -> 156
F13: Identity Verification Rules (PAN/Aadhaar/Passport/VID/DL) | H13: India | I13: R&C | L13: 2 | M13: 8 | P13: 20 | Q13: 24 | R13: 36 | S13: 36 | V13: =SUM(J13:U13) -> 126
F14: Address, Demographic & Document Expiry Validation | H14: India | I14: R&C | M14: 6 | P14: 16 | Q14: 20 | R14: 28 | S14: 28 | V14: =SUM(J14:U14) -> 98
F15: CDD / EDD & Customer Risk Categorisation Validation | H15: India | I15: R&C | L15: 2 | M15: 8 | P15: 16 | Q15: 20 | R15: 28 | S15: 28 | V15: =SUM(J15:U15) -> 102
F16: Periodic KYC Review & FATCA / CRS Compliance Checks | H16: India | I16: R&C | M16: 6 | P16: 12 | Q16: 16 | R16: 24 | S16: 24 | V16: =SUM(J16:U16) -> 82
F17: Exception Detection, Severity Ranking & Bulk Closure | H17: India | I17: R&C | M17: 6 | P17: 16 | Q17: 20 | R17: 28 | S17: 28 | V17: =SUM(J17:U17) -> 98
F18: Automated & Stratified Sampling Engine | H18: India | I18: R&C | M18: 6 | P18: 12 | Q18: 16 | R18: 24 | S18: 24 | V18: =SUM(J18:U18) -> 82
F19: Dynamic KYC Checklist Automation | H19: India | I19: R&C | M19: 4 | P19: 12 | Q19: 16 | R19: 20 | S19: 20 | V19: =SUM(J19:U19) -> 72
F20: No-Code Rule Engine, Versioning & Impact Simulation | H20: India | I20: R&C | L20: 2 | M20: 8 | P20: 16 | Q20: 20 | R20: 32 | S20: 32 | V20: =SUM(J20:U20) -> 110
F21: API Layer & Microservices Implementation | H21: India | I21: R&C | M21: 6 | P21: 16 | Q21: 20 | R21: 32 | S21: 32 | V21: =SUM(J21:U21) -> 106
F22: Frontend Design & Exception / Heat-Map Dashboards | H22: India | I22: R&C | M22: 8 | P22: 20 | Q22: 24 | R22: 36 | S22: 36 | V22: =SUM(J22:U22) -> 124
F23: FE & BE Integration | H23: India | I23: R&C | M23: 6 | P23: 12 | Q23: 20 | R23: 24 | S23: 24 | V23: =SUM(J23:U23) -> 86
F24: Workflow, Query Management & Collaboration | H24: India | I24: R&C | M24: 4 | P24: 12 | Q24: 16 | R24: 24 | S24: 24 | V24: =SUM(J24:U24) -> 80
F25: Reporting Suite (6 standard regulatory reports) | H25: India | I25: R&C | M25: 4 | P25: 12 | Q25: 16 | R25: 20 | S25: 20 | V25: =SUM(J25:U25) -> 72
F26: Auth, RBAC, Audit Trail & NFR Implementation | H26: India | I26: R&C | M26: 6 | P26: 12 | Q26: 16 | R26: 20 | S26: 20 | V26: =SUM(J26:U26) -> 74
F27: Component Testing & SIT | H27: India | I27: R&C | L27: 2 | M27: 6 | P27: 16 | Q27: 24 | R27: 32 | S27: 32 | V27: =SUM(J27:U27) -> 112
F28: User Acceptance Testing (incl. Bug Fixing) | H28: India | I28: R&C | L28: 1 | M28: 4 | P28: 12 | Q28: 16 | R28: 24 | S28: 24 | V28: =SUM(J28:U28) -> 81
F29: Documentation (Technical, User, DR/BCP) | H29: India | I29: R&C | M29: 4 | P29: 8 | Q29: 12 | R29: 16 | S29: 16 | V29: =SUM(J29:U29) -> 56
F30: PMO & Programme Governance | H30: India | I30: R&C | N30: 100 | V30: =SUM(J30:U30) -> 100
F31: Go-live & Hypercare Support | H31: India | I31: R&C | M31: 4 | P31: 8 | Q31: 12 | R31: 12 | S31: 12 | V31: =SUM(J31:U31) -> 48
F32: Handover & Knowledge Transfer | H32: India | I32: R&C | J32: 1 | L32: 4 | M32: 4 | P32: 8 | Q32: 8 | R32: 12 | S32: 12 | V32: =SUM(J32:U32) -> 49
F33: Total | J33: =SUM(J8:J32) -> 6 | K33: =SUM(K8:K32) -> 0 | L33: =SUM(L8:L32) -> 45 | M33: =SUM(M8:M32) -> 158 | N33: =SUM(N8:N32) -> 100 | O33: =SUM(O8:O32) -> 0 | P33: =SUM(P8:P32) -> 344 | Q33: =SUM(Q8:Q32) -> 440 | ... V33: =SUM(V8:V32) -> 2333
H35: Project Mix | J35: =IFERROR(J33/$V$33,0) -> 0.002571796 | K35: =IFERROR(K33/$V$33,0) -> 0 | L35: =IFERROR(L33/$V$33,0) -> 0.01928847 | M35: =IFERROR(M33/$V$33,0) -> 0.067723961 | N35: =IFERROR(N33/$V$33,0) -> 0.042863266 | O35: =IFERROR(O33/$V$33,0) -> 0 | P35: =IFERROR(P33/$V$33,0) -> 0.14744964 | Q35: =IFERROR(Q33/$V$33,0) -> 0.18859837 | ... U35: =IFERROR(U33/$V$33,0) -> 0
A38: F E E B R E A K D O W N | H38: =" All Values in ( "&C7&" )" -> All Values in ( INR ) | L38: What if analysis - FYI Only
A39: Total Engagement Value | D39: 5500000 | E39: Expenses Budgeting | L39: Pricing Tool - Home Office | Q39: Fee Amount | S39: Recovery %
A40: Description | D40: Org./ Name | F40: Hours Breakdown | G40: Fee Breakdown | H40: Budgeted Outlays | L40: Standard Fee | Q40: =$AB$5 -> 14999420 | S40: =$AB$5 -> 14999420
A41: Home Office | D41: =C4 -> India - R&C | F41: =V33 -> 2333 | G41: =D39-(SUM(G42:G45)+H46) -> 5500000 | H41: 0 | L41: ="Proposed Fee (Home Office)"&" - "&IF(D41=0,"",D41) -> Proposed Fee (Home Office) - India - R&C | Q41: =G41 -> 5500000 | S41: =S40*S44 -> 5500000
A42: Sub-Contractor (3rd party) | F42: 0 | G42: 0 | H42: 0 | L42: Planned Fee Adjustment (PFA) | Q42: =Q40-Q41 -> 9499420 | S42: =S40-S41 -> 9499420
F43: 0 | G43: 0 | H43: 0 | L43: PFA % | Q43: =IFERROR(Q42/Q40,0) -> 0.63331916 | S43: =1-S44 -> 0.63331916
F44: 0 | G44: 0 | H44: 0 | L44: Recovery % | Q44: =1-Q43 -> 0.36668084 | S44: =F48 -> 0.36668084
A45: GST | F45: 0 | G45: 0 | H45: 0
A46: Total | F46: =SUM(F41:F45) -> 2333 | G46: =SUM(G41:G45) -> 5500000 | H46: =SUM(H41:H45) -> 0
C48: Budgeted Recovery % | F48: =IFERROR(G41/$AB$5,0) -> 0.36668084
L49: Gross Fee | N49: Net Fee | P49: Net CM | R49: Gross CM
L50: Fee | M50: Per/Hr | N50: Fee | O50: Per/Hr | P50: % | R50: % | T50: Margin | V50: Staff Cost
K51: =C7 -> INR | L51: =G46 -> 5500000 | M51: =IFERROR(L51/F46,0) -> 2357.4796 | N51: =G41 -> 5500000 | O51: =IFERROR(N51/V33,0) -> 2357.4796 | P51: =IFERROR((T51-(N51*5%))/N51,0) -> 0.25976 | R51: =IFERROR((L51-V51-(G46-G41)-(N51*5%))/L51,0) -> 0.25976 | T51: =IFERROR(N51-V51,0) -> 1703680 | V51: =IFERROR($AB$6,0) -> 3796320
D53: Data to be entered / editable | L53: Gross Contribution Margin is derived after considering direct staff cost, management fees, Sub-contractor cost and other direct cost. Net Contribution Margin is derived after considering direct staff cost, management fees and other direct cost.
D54: Calculated - do not overwrite

Sheet 5. Checklist Automation
A1: Protiviti Member Firm (India) | V1: Project Template 2023 Apr.23
A2: Project Template - Fixed Fee Inclusive Outlays
A4: Organisation: | C4: India - R&C | X4: < Summary | Z4: RATE ENGINE (auto)
A5: Client Legal Name: | C5: YES BANK Ltd. | F5: Resource Plan (Home Office) - Budgeted Hours by Task and Resource Category | Z5: Standard Revenue (INR) | AB5: =SUMPRODUCT(J28:U28,Ratesheet!$B$23:$M$23) -> 8438810
A6: Project Description: | C6: Audit Checklist Automation | F6: Task Name | H6: Business Unit | J6: MD | K6: SD | L6: DIR | M6: AD | N6: SR. MGR | O6: MGR | P6: DM | Q6: SR. CONS. | R6: CON3 | S6: CON2 | T6: CON1 | U6: ANLST. | V6: TOTAL | X6: Ratesheet | Z6: Standard Staff Cost (INR) | AB6: =SUMPRODUCT(J28:U28,Ratesheet!$B$24:$M$24) -> 2152848
A7: Billing Currency: | C7: INR | H7: Country | I7: Service line | Z7: Blended chargeout / hr | AB7: =IFERROR(AB5/V28,0) -> 6556.9619
A8: Project Type: | C8: Fixed Fee (Incl. Outlays) | F8: Requirement Gathering & Regulatory Corpus Study | H8: India | I8: R&C | J8: 1 | L8: 6 | M8: 8 | P8: 12 | Q8: 12 | R8: 12 | S8: 12 | V8: =SUM(J8:U8) -> 63 | Z8: Blended cost / hr | AB8: =IFERROR(AB6/V28,0) -> 1672.7646
F9: Technical Architecture, Design & Planning | H9: India | I9: R&C | J9: 1 | L9: 6 | M9: 6 | P9: 8 | Q9: 12 | R9: 12 | S9: 12 | V9: =SUM(J9:U9) -> 57
F10: Data Model & Central Rule Repository Design | H10: India | I10: R&C | L10: 2 | M10: 6 | P10: 12 | Q10: 12 | R10: 16 | S10: 16 | V10: =SUM(J10:U10) -> 64
F11: Regulatory / Circular / SOP Ingestion Pipeline | H11: India | I11: R&C | L11: 2 | M11: 6 | P11: 16 | Q11: 20 | R11: 28 | S11: 28 | V11: =SUM(J11:U11) -> 100
F12: NLP Extraction & Requirement Interpretation | H12: India | I12: R&C | L12: 4 | M12: 8 | P12: 16 | Q12: 20 | R12: 28 | S12: 28 | V12: =SUM(J12:U12) -> 104
F13: Regulation-to-Control Mapping Repository | H13: India | I13: R&C | L13: 2 | M13: 6 | P13: 12 | Q13: 16 | R13: 24 | S13: 24 | V13: =SUM(J13:U13) -> 84
F14: Checklist Generation Engine (process / entity / risk-wise) | H14: India | I14: R&C | L14: 2 | M14: 6 | P14: 12 | Q14: 16 | R14: 24 | S14: 24 | V14: =SUM(J14:U14) -> 84
F15: Auto-Update on Regulatory Change & Traceability | H15: India | I15: R&C | M15: 4 | P15: 12 | Q15: 16 | R15: 20 | S15: 20 | V15: =SUM(J15:U15) -> 72
F16: Version Control, Approval Workflow & Audit Trail | H16: India | I16: R&C | M16: 4 | P16: 8 | Q16: 12 | R16: 16 | S16: 16 | V16: =SUM(J16:U16) -> 56
F17: Auditor Customisation & Evidence Tagging | H17: India | I17: R&C | M17: 4 | P17: 8 | Q17: 12 | R17: 16 | S17: 16 | V17: =SUM(J17:U17) -> 56
F18: API Layer & Integration with ALCM / Pre-Audit | H18: India | I18: R&C | M18: 4 | P18: 8 | Q18: 12 | R18: 20 | S18: 20 | V18: =SUM(J18:U18) -> 64
F19: Frontend Design & Checklist Console | H19: India | I19: R&C | M19: 6 | P19: 12 | Q19: 20 | R19: 24 | S19: 24 | V19: =SUM(J19:U19) -> 86
F20: FE & BE Integration | H20: India | I20: R&C | M20: 4 | P20: 8 | Q20: 12 | R20: 16 | S20: 16 | V20: =SUM(J20:U20) -> 56
F21: Auth, RBAC, Audit Trail & NFR Implementation | H21: India | I21: R&C | M21: 4 | P21: 8 | Q21: 12 | R21: 12 | S21: 12 | V21: =SUM(J21:U21) -> 48
F22: Component Testing & SIT | H22: India | I22: R&C | L22: 1 | M22: 4 | P22: 8 | Q22: 16 | R22: 20 | S22: 20 | V22: =SUM(J22:U22) -> 69
F23: User Acceptance Testing (incl. Bug Fixing) | H23: India | I23: R&C | L23: 1 | M23: 4 | P23: 8 | Q23: 12 | R23: 16 | S23: 16 | V23: =SUM(J23:U23) -> 57
F24: Documentation (Technical, User) | H24: India | I24: R&C | M24: 2 | P24: 8 | Q24: 8 | R24: 12 | S24: 12 | V24: =SUM(J24:U24) -> 42
F25: PMO & Programme Governance | H25: India | I25: R&C | N25: 60 | V25: =SUM(J25:U25) -> 60
F26: Go-live & Hypercare Support | H26: India | I26: R&C | M26: 2 | P26: 4 | Q26: 8 | R26: 8 | S26: 8 | V26: =SUM(J26:U26) -> 30
F27: Handover & Knowledge Transfer | H27: India | I27: R&C | J27: 1 | L27: 2 | M27: 4 | P27: 4 | Q27: 8 | R27: 8 | S27: 8 | V27: =SUM(J27:U27) -> 35
F28: Total | J28: =SUM(J8:J27) -> 3 | K28: =SUM(K8:K27) -> 0 | L28: =SUM(L8:L27) -> 28 | M28: =SUM(M8:M27) -> 92 | N28: =SUM(N8:N27) -> 60 | O28: =SUM(O8:O27) -> 0 | P28: =SUM(P8:P27) -> 184 | Q28: =SUM(Q8:Q27) -> 256 | ... V28: =SUM(V8:V27) -> 1287
H30: Project Mix | J30: =IFERROR(J28/$V$28,0) -> 0.0023310023 | K30: =IFERROR(K28/$V$28,0) -> 0 | L30: =IFERROR(L28/$V$28,0) -> 0.021756022 | M30: =IFERROR(M28/$V$28,0) -> 0.071484071 | N30: =IFERROR(N28/$V$28,0) -> 0.046620047 | O30: =IFERROR(O28/$V$28,0) -> 0 | P30: =IFERROR(P28/$V$28,0) -> 0.14296814 | Q30: =IFERROR(Q28/$V$28,0) -> 0.1989122 | ... U30: =IFERROR(U28/$V$28,0) -> 0
A33: F E E B R E A K D O W N | H33: =" All Values in ( "&C7&" )" -> All Values in ( INR ) | L33: What if analysis - FYI Only
A34: Total Engagement Value | D34: 3250000 | E34: Expenses Budgeting | L34: Pricing Tool - Home Office | Q34: Fee Amount | S34: Recovery %
A35: Description | D35: Org./ Name | F35: Hours Breakdown | G35: Fee Breakdown | H35: Budgeted Outlays | L35: Standard Fee | Q35: =$AB$5 -> 8438810 | S35: =$AB$5 -> 8438810
A36: Home Office | D36: =C4 -> India - R&C | F36: =V28 -> 1287 | G36: =D34-(SUM(G37:G40)+H41) -> 3250000 | H36: 0 | L36: ="Proposed Fee (Home Office)"&" - "&IF(D36=0,"",D36) -> Proposed Fee (Home Office) - India - R&C | Q36: =G36 -> 3250000 | S36: =S35*S39 -> 3250000
A37: Sub-Contractor (3rd party) | F37: 0 | G37: 0 | H37: 0 | L37: Planned Fee Adjustment (PFA) | Q37: =Q35-Q36 -> 5188810 | S37: =S35-S36 -> 5188810
F38: 0 | G38: 0 | H38: 0 | L38: PFA % | Q38: =IFERROR(Q37/Q35,0) -> 0.61487461 | S38: =1-S39 -> 0.61487461
F39: 0 | G39: 0 | H39: 0 | L39: Recovery % | Q39: =1-Q38 -> 0.38512539 | S39: =F43 -> 0.38512539
A40: GST | F40: 0 | G40: 0 | H40: 0
A41: Total | F41: =SUM(F36:F40) -> 1287 | G41: =SUM(G36:G40) -> 3250000 | H41: =SUM(H36:H40) -> 0
C43: Budgeted Recovery % | F43: =IFERROR(G36/$AB$5,0) -> 0.38512539
L44: Gross Fee | N44: Net Fee | P44: Net CM | R44: Gross CM
L45: Fee | M45: Per/Hr | N45: Fee | O45: Per/Hr | P45: % | R45: % | T45: Margin | V45: Staff Cost
K46: =C7 -> INR | L46: =G41 -> 3250000 | M46: =IFERROR(L46/F41,0) -> 2525.2525 | N46: =G36 -> 3250000 | O46: =IFERROR(N46/V28,0) -> 2525.2525 | P46: =IFERROR((T46-(N46*5%))/N46,0) -> 0.28758523 | R46: =IFERROR((L46-V46-(G41-G36)-(N46*5%))/L46,0) -> 0.28758523 | T46: =IFERROR(N46-V46,0) -> 1097152 | V46: =IFERROR($AB$6,0) -> 2152848
D48: Data to be entered / editable | L48: Gross Contribution Margin is derived after considering direct staff cost, management fees, Sub-contractor cost and other direct cost. Net Contribution Margin is derived after considering direct staff cost, management fees and other direct cost.
D49: Calculated - do not overwrite

Sheet 6. Data Analytics
A1: Protiviti Member Firm (India) | V1: Project Template 2023 Apr.23
A2: Project Template - Fixed Fee Inclusive Outlays
A4: Organisation: | C4: India - R&C | X4: < Summary | Z4: RATE ENGINE (auto)
A5: Client Legal Name: | C5: YES BANK Ltd. | F5: Resource Plan (Home Office) - Budgeted Hours by Task and Resource Category | Z5: Standard Revenue (INR) | AB5: =SUMPRODUCT(J34:U34,Ratesheet!$B$23:$M$23) -> 16830130
A6: Project Description: | C6: Data Analytics for Internal Audit (AI/ML) | F6: Task Name | H6: Business Unit | J6: MD | K6: SD | L6: DIR | M6: AD | N6: SR. MGR | O6: MGR | P6: DM | Q6: SR. CONS. | R6: CON3 | S6: CON2 | T6: CON1 | U6: ANLST. | V6: TOTAL | X6: Ratesheet | Z6: Standard Staff Cost (INR) | AB6: =SUMPRODUCT(J34:U34,Ratesheet!$B$24:$M$24) -> 4322544
A7: Billing Currency: | C7: INR | H7: Country | I7: Service line | Z7: Blended chargeout / hr | AB7: =IFERROR(AB5/V34,0) -> 6620.8222
A8: Project Type: | C8: Fixed Fee (Incl. Outlays) | F8: Requirement Gathering & Analytics Use-Case Definition | H8: India | I8: R&C | J8: 2 | L8: 10 | M8: 10 | P8: 16 | Q8: 16 | R8: 20 | S8: 20 | V8: =SUM(J8:U8) -> 94 | Z8: Blended cost / hr | AB8: =IFERROR(AB6/V34,0) -> 1700.45
F9: Technical Architecture, Design & Planning (MLOps) | H9: India | I9: R&C | J9: 2 | L9: 12 | M9: 12 | P9: 16 | Q9: 16 | R9: 16 | S9: 16 | V9: =SUM(J9:U9) -> 90
F10: Data Model, Feature Store & Lakehouse Design | H10: India | I10: R&C | L10: 6 | M10: 10 | P10: 16 | Q10: 20 | R10: 28 | S10: 28 | V10: =SUM(J10:U10) -> 108
F11: Multi-Source Data Ingestion & Pipelines | H11: India | I11: R&C | L11: 4 | M11: 8 | P11: 20 | Q11: 28 | R11: 44 | S11: 44 | V11: =SUM(J11:U11) -> 148
F12: AI-Enabled Data Profiling & Quality Scoring | H12: India | I12: R&C | L12: 2 | M12: 8 | P12: 16 | Q12: 20 | R12: 32 | S12: 32 | V12: =SUM(J12:U12) -> 110
F13: Automated Data Cleaning & Transformation Pipelines | H13: India | I13: R&C | M13: 6 | P13: 16 | Q13: 20 | R13: 32 | S13: 32 | V13: =SUM(J13:U13) -> 106
F14: Anomaly & Outlier Detection Models | H14: India | I14: R&C | L14: 4 | M14: 12 | P14: 24 | Q14: 28 | R14: 40 | S14: 40 | V14: =SUM(J14:U14) -> 148
F15: Predictive Risk Modelling & Forecasting | H15: India | I15: R&C | L15: 4 | M15: 12 | P15: 20 | Q15: 24 | R15: 36 | S15: 36 | V15: =SUM(J15:U15) -> 132
F16: Intelligent Segmentation & Clustering | H16: India | I16: R&C | L16: 2 | M16: 8 | P16: 16 | Q16: 20 | R16: 28 | S16: 28 | V16: =SUM(J16:U16) -> 102
F17: ML-Based Exception Scoring & Feedback Learning | H17: India | I17: R&C | L17: 2 | M17: 8 | P17: 16 | Q17: 20 | R17: 28 | S17: 28 | V17: =SUM(J17:U17) -> 102
F18: Intelligent / Risk-Based Sampling Models | H18: India | I18: R&C | L18: 2 | M18: 6 | P18: 12 | Q18: 16 | R18: 24 | S18: 24 | V18: =SUM(J18:U18) -> 84
F19: NLP Models for Documents, Policies & Circulars | H19: India | I19: R&C | L19: 4 | M19: 10 | P19: 20 | Q19: 24 | R19: 32 | S19: 32 | V19: =SUM(J19:U19) -> 122
F20: Explainable AI (SHAP / LIME) Layer | H20: India | I20: R&C | L20: 2 | M20: 8 | P20: 16 | Q20: 20 | R20: 24 | S20: 24 | V20: =SUM(J20:U20) -> 94
F21: Model Registry, Versioning & Governance | H21: India | I21: R&C | L21: 2 | M21: 8 | P21: 16 | Q21: 20 | R21: 24 | S21: 24 | V21: =SUM(J21:U21) -> 94
F22: Model Drift, Bias & Performance Monitoring | H22: India | I22: R&C | L22: 2 | M22: 6 | P22: 16 | Q22: 20 | R22: 24 | S22: 24 | V22: =SUM(J22:U22) -> 92
F23: Controlled Re-training & Approval Workflow | H23: India | I23: R&C | M23: 4 | P23: 12 | Q23: 16 | R23: 20 | S23: 20 | V23: =SUM(J23:U23) -> 72
F24: API Layer & Microservices Implementation | H24: India | I24: R&C | M24: 6 | P24: 16 | Q24: 20 | R24: 32 | S24: 32 | V24: =SUM(J24:U24) -> 106
F25: Frontend Design & AI Insight Dashboards | H25: India | I25: R&C | M25: 8 | P25: 20 | Q25: 24 | R25: 36 | S25: 36 | V25: =SUM(J25:U25) -> 124
F26: FE & BE Integration | H26: India | I26: R&C | M26: 6 | P26: 12 | Q26: 20 | R26: 24 | S26: 24 | V26: =SUM(J26:U26) -> 86
F27: Auth, RBAC, Data Lineage & NFR Implementation | H27: India | I27: R&C | M27: 6 | P27: 12 | Q27: 16 | R27: 20 | S27: 20 | V27: =SUM(J27:U27) -> 74
F28: Component Testing, Model Validation & SIT | H28: India | I28: R&C | L28: 2 | M28: 8 | P28: 16 | Q28: 24 | R28: 32 | S28: 32 | V28: =SUM(J28:U28) -> 114
F29: User Acceptance Testing (incl. Bug Fixing) | H29: India | I29: R&C | L29: 1 | M29: 4 | P29: 12 | Q29: 16 | R29: 20 | S29: 20 | V29: =SUM(J29:U29) -> 73
F30: Documentation (Architecture, Model Cards, Runbooks) | H30: India | I30: R&C | M30: 4 | P30: 12 | Q30: 12 | R30: 16 | S30: 16 | V30: =SUM(J30:U30) -> 60
F31: PMO & Programme Governance | H31: India | I31: R&C | N31: 110 | V31: =SUM(J31:U31) -> 110
F32: Go-live & Hypercare Support | H32: India | I32: R&C | M32: 4 | P32: 8 | Q32: 12 | R32: 12 | S32: 12 | V32: =SUM(J32:U32) -> 48
F33: Handover & Knowledge Transfer | H33: India | I33: R&C | J33: 1 | L33: 4 | M33: 4 | P33: 8 | Q33: 8 | R33: 12 | S33: 12 | V33: =SUM(J33:U33) -> 49
F34: Total | J34: =SUM(J8:J33) -> 5 | K34: =SUM(K8:K33) -> 0 | L34: =SUM(L8:L33) -> 65 | M34: =SUM(M8:M33) -> 186 | N34: =SUM(N8:N33) -> 110 | O34: =SUM(O8:O33) -> 0 | P34: =SUM(P8:P33) -> 384 | Q34: =SUM(Q8:Q33) -> 480 | ... V34: =SUM(V8:V33) -> 2542
H36: Project Mix | J36: =IFERROR(J34/$V$34,0) -> 0.0019669552 | K36: =IFERROR(K34/$V$34,0) -> 0 | L36: =IFERROR(L34/$V$34,0) -> 0.025570417 | M36: =IFERROR(M34/$V$34,0) -> 0.073170732 | N36: =IFERROR(N34/$V$34,0) -> 0.043273013 | O36: =IFERROR(O34/$V$34,0) -> 0 | P36: =IFERROR(P34/$V$34,0) -> 0.15106216 | Q36: =IFERROR(Q34/$V$34,0) -> 0.18882769 | ... U36: =IFERROR(U34/$V$34,0) -> 0
A39: F E E B R E A K D O W N | H39: =" All Values in ( "&C7&" )" -> All Values in ( INR ) | L39: What if analysis - FYI Only
A40: Total Engagement Value | D40: 6750000 | E40: Expenses Budgeting | L40: Pricing Tool - Home Office | Q40: Fee Amount | S40: Recovery %
A41: Description | D41: Org./ Name | F41: Hours Breakdown | G41: Fee Breakdown | H41: Budgeted Outlays | L41: Standard Fee | Q41: =$AB$5 -> 16830130 | S41: =$AB$5 -> 16830130
A42: Home Office | D42: =C4 -> India - R&C | F42: =V34 -> 2542 | G42: =D40-(SUM(G43:G46)+H47) -> 6750000 | H42: 0 | L42: ="Proposed Fee (Home Office)"&" - "&IF(D42=0,"",D42) -> Proposed Fee (Home Office) - India - R&C | Q42: =G42 -> 6750000 | S42: =S41*S45 -> 6750000
A43: Sub-Contractor (3rd party) | F43: 0 | G43: 0 | H43: 0 | L43: Planned Fee Adjustment (PFA) | Q43: =Q41-Q42 -> 10080130 | S43: =S41-S42 -> 10080130
F44: 0 | G44: 0 | H44: 0 | L44: PFA % | Q44: =IFERROR(Q43/Q41,0) -> 0.59893358 | S44: =1-S45 -> 0.59893358
F45: 0 | G45: 0 | H45: 0 | L45: Recovery % | Q45: =1-Q44 -> 0.40106642 | S45: =F49 -> 0.40106642
A46: GST | F46: 0 | G46: 0 | H46: 0
A47: Total | F47: =SUM(F42:F46) -> 2542 | G47: =SUM(G42:G46) -> 6750000 | H47: =SUM(H42:H46) -> 0
C49: Budgeted Recovery % | F49: =IFERROR(G42/$AB$5,0) -> 0.40106642
L50: Gross Fee | N50: Net Fee | P50: Net CM | R50: Gross CM
L51: Fee | M51: Per/Hr | N51: Fee | O51: Per/Hr | P51: % | R51: % | T51: Margin | V51: Staff Cost
K52: =C7 -> INR | L52: =G47 -> 6750000 | M52: =IFERROR(L52/F47,0) -> 2655.3895 | N52: =G42 -> 6750000 | O52: =IFERROR(N52/V34,0) -> 2655.3895 | P52: =IFERROR((T52-(N52*5%))/N52,0) -> 0.30962311 | R52: =IFERROR((L52-V52-(G47-G42)-(N52*5%))/L52,0) -> 0.30962311 | T52: =IFERROR(N52-V52,0) -> 2427456 | V52: =IFERROR($AB$6,0) -> 4322544
D54: Data to be entered / editable | L54: Gross Contribution Margin is derived after considering direct staff cost, management fees, Sub-contractor cost and other direct cost. Net Contribution Margin is derived after considering direct staff cost, management fees and other direct cost.
D55: Calculated - do not overwrite

Sheet 7. ALCM
A1: Protiviti Member Firm (India) | V1: Project Template 2023 Apr.23
A2: Project Template - Fixed Fee Inclusive Outlays
A4: Organisation: | C4: India - R&C | X4: < Summary | Z4: RATE ENGINE (auto)
A5: Client Legal Name: | C5: YES BANK Ltd. | F5: Resource Plan (Home Office) - Budgeted Hours by Task and Resource Category | Z5: Standard Revenue (INR) | AB5: =SUMPRODUCT(J31:U31,Ratesheet!$B$23:$M$23) -> 13756660
A6: Project Description: | C6: Audit Life Cycle Management (ALCM) | F6: Task Name | H6: Business Unit | J6: MD | K6: SD | L6: DIR | M6: AD | N6: SR. MGR | O6: MGR | P6: DM | Q6: SR. CONS. | R6: CON3 | S6: CON2 | T6: CON1 | U6: ANLST. | V6: TOTAL | X6: Ratesheet | Z6: Standard Staff Cost (INR) | AB6: =SUMPRODUCT(J31:U31,Ratesheet!$B$24:$M$24) -> 3493176
A7: Billing Currency: | C7: INR | H7: Country | I7: Service line | Z7: Blended chargeout / hr | AB7: =IFERROR(AB5/V31,0) -> 6449.4421
A8: Project Type: | C8: Fixed Fee (Incl. Outlays) | F8: Requirement Gathering & Audit Lifecycle Process Study | H8: India | I8: R&C | J8: 2 | L8: 10 | M8: 10 | P8: 16 | Q8: 16 | R8: 20 | S8: 20 | V8: =SUM(J8:U8) -> 94 | Z8: Blended cost / hr | AB8: =IFERROR(AB6/V31,0) -> 1637.6821
F9: Technical Architecture, Design & Planning | H9: India | I9: R&C | J9: 2 | L9: 10 | M9: 10 | P9: 12 | Q9: 12 | R9: 16 | S9: 16 | V9: =SUM(J9:U9) -> 78
F10: Data Model & Database Design | H10: India | I10: R&C | J10: 1 | L10: 4 | M10: 6 | P10: 12 | Q10: 16 | R10: 20 | S10: 20 | V10: =SUM(J10:U10) -> 79
F11: Audit Planning, Universe & Scheduling Module | H11: India | I11: R&C | L11: 2 | M11: 8 | P11: 20 | Q11: 24 | R11: 36 | S11: 36 | V11: =SUM(J11:U11) -> 126
F12: Audit Scope & Programme Definition Module | H12: India | I12: R&C | L12: 2 | M12: 6 | P12: 16 | Q12: 20 | R12: 28 | S12: 28 | V12: =SUM(J12:U12) -> 100
F13: Fieldwork & Workpaper Documentation Module | H13: India | I13: R&C | L13: 2 | M13: 8 | P13: 20 | Q13: 28 | R13: 40 | S13: 40 | V13: =SUM(J13:U13) -> 138
F14: Findings & Issue Management Module | H14: India | I14: R&C | M14: 6 | P14: 16 | Q14: 20 | R14: 32 | S14: 32 | V14: =SUM(J14:U14) -> 106
F15: Reporting, QA Review & Report Release Workflow | H15: India | I15: R&C | L15: 2 | M15: 6 | P15: 16 | Q15: 20 | R15: 32 | S15: 32 | V15: =SUM(J15:U15) -> 108
F16: Action Tracking, Follow-Up & Audit Closure | H16: India | I16: R&C | M16: 6 | P16: 12 | Q16: 16 | R16: 24 | S16: 24 | V16: =SUM(J16:U16) -> 82
F17: Resource Allocation & Schedule Management | H17: India | I17: R&C | M17: 4 | P17: 12 | Q17: 16 | R17: 20 | S17: 20 | V17: =SUM(J17:U17) -> 72
F18: Configurable Workflow & Approval Engine | H18: India | I18: R&C | L18: 2 | M18: 6 | P18: 16 | Q18: 20 | R18: 28 | S18: 28 | V18: =SUM(J18:U18) -> 100
F19: API Layer & Integration with CCM / Analytics / Checklist | H19: India | I19: R&C | L19: 2 | M19: 6 | P19: 16 | Q19: 20 | R19: 32 | S19: 32 | V19: =SUM(J19:U19) -> 108
F20: Pentana Migration & Historical Data Migration Utility | H20: India | I20: R&C | L20: 2 | M20: 6 | P20: 16 | Q20: 20 | R20: 28 | S20: 28 | V20: =SUM(J20:U20) -> 100
F21: Frontend Design & Audit Status Dashboards | H21: India | I21: R&C | M21: 8 | P21: 20 | Q21: 28 | R21: 40 | S21: 40 | V21: =SUM(J21:U21) -> 136
F22: FE & BE Integration | H22: India | I22: R&C | M22: 6 | P22: 16 | Q22: 20 | R22: 24 | S22: 24 | V22: =SUM(J22:U22) -> 90
F23: Mobile-Responsive UI & Offline Sync Capability | H23: India | I23: R&C | M23: 4 | P23: 12 | Q23: 16 | R23: 24 | S23: 24 | V23: =SUM(J23:U23) -> 80
F24: Auth, RBAC, SoD, Audit Trail & NFR Implementation | H24: India | I24: R&C | M24: 6 | P24: 16 | Q24: 20 | R24: 24 | S24: 24 | V24: =SUM(J24:U24) -> 90
F25: Component Testing & SIT | H25: India | I25: R&C | L25: 2 | M25: 6 | P25: 16 | Q25: 24 | R25: 32 | S25: 32 | V25: =SUM(J25:U25) -> 112
F26: User Acceptance Testing (incl. Bug Fixing) | H26: India | I26: R&C | L26: 1 | M26: 4 | P26: 12 | Q26: 16 | R26: 24 | S26: 24 | V26: =SUM(J26:U26) -> 81
F27: Documentation (Technical, User, DR/BCP) | H27: India | I27: R&C | M27: 4 | P27: 8 | Q27: 12 | R27: 16 | S27: 16 | V27: =SUM(J27:U27) -> 56
F28: PMO & Programme Governance | H28: India | I28: R&C | N28: 100 | V28: =SUM(J28:U28) -> 100
F29: Go-live & Hypercare Support | H29: India | I29: R&C | M29: 4 | P29: 8 | Q29: 12 | R29: 12 | S29: 12 | V29: =SUM(J29:U29) -> 48
F30: Handover & Knowledge Transfer | H30: India | I30: R&C | J30: 1 | L30: 4 | M30: 4 | P30: 8 | Q30: 8 | R30: 12 | S30: 12 | V30: =SUM(J30:U30) -> 49
F31: Total | J31: =SUM(J8:J30) -> 6 | K31: =SUM(K8:K30) -> 0 | L31: =SUM(L8:L30) -> 45 | M31: =SUM(M8:M30) -> 134 | N31: =SUM(N8:N30) -> 100 | O31: =SUM(O8:O30) -> 0 | P31: =SUM(P8:P30) -> 316 | Q31: =SUM(Q8:Q30) -> 404 | ... V31: =SUM(V8:V30) -> 2133
H33: Project Mix | J33: =IFERROR(J31/$V$31,0) -> 0.0028129395 | K33: =IFERROR(K31/$V$31,0) -> 0 | L33: =IFERROR(L31/$V$31,0) -> 0.021097046 | M33: =IFERROR(M31/$V$31,0) -> 0.062822316 | N33: =IFERROR(N31/$V$31,0) -> 0.046882325 | O33: =IFERROR(O31/$V$31,0) -> 0 | P33: =IFERROR(P31/$V$31,0) -> 0.14814815 | Q33: =IFERROR(Q31/$V$31,0) -> 0.18940459 | ... U33: =IFERROR(U31/$V$31,0) -> 0
A36: F E E B R E A K D O W N | H36: =" All Values in ( "&C7&" )" -> All Values in ( INR ) | L36: What if analysis - FYI Only
A37: Total Engagement Value | D37: 4750000 | E37: Expenses Budgeting | L37: Pricing Tool - Home Office | Q37: Fee Amount | S37: Recovery %
A38: Description | D38: Org./ Name | F38: Hours Breakdown | G38: Fee Breakdown | H38: Budgeted Outlays | L38: Standard Fee | Q38: =$AB$5 -> 13756660 | S38: =$AB$5 -> 13756660
A39: Home Office | D39: =C4 -> India - R&C | F39: =V31 -> 2133 | G39: =D37-(SUM(G40:G43)+H44) -> 4750000 | H39: 0 | L39: ="Proposed Fee (Home Office)"&" - "&IF(D39=0,"",D39) -> Proposed Fee (Home Office) - India - R&C | Q39: =G39 -> 4750000 | S39: =S38*S42 -> 4750000
A40: Sub-Contractor (3rd party) | F40: 0 | G40: 0 | H40: 0 | L40: Planned Fee Adjustment (PFA) | Q40: =Q38-Q39 -> 9006660 | S40: =S38-S39 -> 9006660
F41: 0 | G41: 0 | H41: 0 | L41: PFA % | Q41: =IFERROR(Q40/Q38,0) -> 0.6547127 | S41: =1-S42 -> 0.6547127
F42: 0 | G42: 0 | H42: 0 | L42: Recovery % | Q42: =1-Q41 -> 0.3452873 | S42: =F46 -> 0.3452873
A43: GST | F43: 0 | G43: 0 | H43: 0
A44: Total | F44: =SUM(F39:F43) -> 2133 | G44: =SUM(G39:G43) -> 4750000 | H44: =SUM(H39:H43) -> 0
C46: Budgeted Recovery % | F46: =IFERROR(G39/$AB$5,0) -> 0.3452873
L47: Gross Fee | N47: Net Fee | P47: Net CM | R47: Gross CM
L48: Fee | M48: Per/Hr | N48: Fee | O48: Per/Hr | P48: % | R48: % | T48: Margin | V48: Staff Cost
K49: =C7 -> INR | L49: =G44 -> 4750000 | M49: =IFERROR(L49/F44,0) -> 2226.9105 | N49: =G39 -> 4750000 | O49: =IFERROR(N49/V31,0) -> 2226.9105 | P49: =IFERROR((T49-(N49*5%))/N49,0) -> 0.21459453 | R49: =IFERROR((L49-V49-(G44-G39)-(N49*5%))/L49,0) -> 0.21459453 | T49: =IFERROR(N49-V49,0) -> 1256824 | V49: =IFERROR($AB$6,0) -> 3493176
D51: Data to be entered / editable | L51: Gross Contribution Margin is derived after considering direct staff cost, management fees, Sub-contractor cost and other direct cost. Net Contribution Margin is derived after considering direct staff cost, management fees and other direct cost.
D52: Calculated - do not overwrite

Sheet 8. Agentic AI
A1: Protiviti Member Firm (India) | V1: Project Template 2023 Apr.23
A2: Project Template - Fixed Fee Inclusive Outlays
A4: Organisation: | C4: India - R&C | X4: < Summary | Z4: RATE ENGINE (auto)
A5: Client Legal Name: | C5: YES BANK Ltd. | F5: Resource Plan (Home Office) - Budgeted Hours by Task and Resource Category | Z5: Standard Revenue (INR) | AB5: =SUMPRODUCT(J36:U36,Ratesheet!$B$23:$M$23) -> 21105590
A6: Project Description: | C6: Agentic AI for Audit Functions | F6: Task Name | H6: Business Unit | J6: MD | K6: SD | L6: DIR | M6: AD | N6: SR. MGR | O6: MGR | P6: DM | Q6: SR. CONS. | R6: CON3 | S6: CON2 | T6: CON1 | U6: ANLST. | V6: TOTAL | X6: Ratesheet | Z6: Standard Staff Cost (INR) | AB6: =SUMPRODUCT(J36:U36,Ratesheet!$B$24:$M$24) -> 5428344
A7: Billing Currency: | C7: INR | H7: Country | I7: Service line | Z7: Blended chargeout / hr | AB7: =IFERROR(AB5/V36,0) -> 6662.1181
A8: Project Type: | C8: Fixed Fee (Incl. Outlays) | F8: Requirement Gathering & Agentic Use-Case Definition | H8: India | I8: R&C | J8: 2 | L8: 12 | M8: 12 | P8: 16 | Q8: 16 | R8: 20 | S8: 20 | V8: =SUM(J8:U8) -> 98 | Z8: Blended cost / hr | AB8: =IFERROR(AB6/V36,0) -> 1713.4924
F9: Agentic Architecture, Design & Planning | H9: India | I9: R&C | J9: 2 | L9: 16 | M9: 16 | P9: 20 | Q9: 20 | R9: 20 | S9: 20 | V9: =SUM(J9:U9) -> 114
F10: In-Perimeter LLM Hosting, GPU Sizing & Model Selection | H10: India | I10: R&C | L10: 6 | M10: 12 | P10: 24 | Q10: 28 | R10: 36 | S10: 36 | V10: =SUM(J10:U10) -> 142
F11: Agent Orchestration Framework & Task Planner | H11: India | I11: R&C | L11: 6 | M11: 16 | P11: 28 | Q11: 36 | R11: 52 | S11: 52 | V11: =SUM(J11:U11) -> 190
F12: Tool / Function Layer (data, test, evidence connectors) | H12: India | I12: R&C | L12: 4 | M12: 12 | P12: 24 | Q12: 32 | R12: 48 | S12: 48 | V12: =SUM(J12:U12) -> 168
F13: Contextual Reasoning & Audit Knowledge Grounding | H13: India | I13: R&C | L13: 4 | M13: 12 | P13: 20 | Q13: 28 | R13: 40 | S13: 40 | V13: =SUM(J13:U13) -> 144
F14: AI-Driven Audit Planning & Scoping Agent | H14: India | I14: R&C | L14: 2 | M14: 8 | P14: 16 | Q14: 20 | R14: 32 | S14: 32 | V14: =SUM(J14:U14) -> 110
F15: AI-Generated Checklist & Test Procedure Agent | H15: India | I15: R&C | L15: 2 | M15: 8 | P15: 16 | Q15: 20 | R15: 28 | S15: 28 | V15: =SUM(J15:U15) -> 102
F16: Agentic Data Analytics & Automated Testing Agent | H16: India | I16: R&C | L16: 4 | M16: 12 | P16: 24 | Q16: 28 | R16: 40 | S16: 40 | V16: =SUM(J16:U16) -> 148
F17: Autonomous Exception Identification & Severity Agent | H17: India | I17: R&C | L17: 2 | M17: 8 | P17: 16 | Q17: 20 | R17: 32 | S17: 32 | V17: =SUM(J17:U17) -> 110
F18: Intelligent Sampling Agent | H18: India | I18: R&C | M18: 6 | P18: 12 | Q18: 16 | R18: 24 | S18: 24 | V18: =SUM(J18:U18) -> 82
F19: Audit Workpaper Generation Agent | H19: India | I19: R&C | L19: 2 | M19: 8 | P19: 16 | Q19: 20 | R19: 32 | S19: 32 | V19: =SUM(J19:U19) -> 110
F20: Autonomous Query Management Agent | H20: India | I20: R&C | M20: 6 | P20: 16 | Q20: 20 | R20: 28 | S20: 28 | V20: =SUM(J20:U20) -> 98
F21: GenAI Report & Narrative Generation (4 summary levels) | H21: India | I21: R&C | L21: 4 | M21: 10 | P21: 20 | Q21: 24 | R21: 36 | S21: 36 | V21: =SUM(J21:U21) -> 130
F22: Explainability, Reasoning Chains & Immutable Logging | H22: India | I22: R&C | L22: 4 | M22: 10 | P22: 20 | Q22: 24 | R22: 32 | S22: 32 | V22: =SUM(J22:U22) -> 122
F23: Human-in-the-Loop Control Plane & Override Workflow | H23: India | I23: R&C | L23: 2 | M23: 8 | P23: 16 | Q23: 20 | R23: 28 | S23: 28 | V23: =SUM(J23:U23) -> 102
F24: Guardrails: Prompt Injection, Data Leakage, Adversarial | H24: India | I24: R&C | L24: 4 | M24: 12 | P24: 20 | Q24: 24 | R24: 32 | S24: 32 | V24: =SUM(J24:U24) -> 124
F25: Agent / Model Registry, Versioning, Rollback & Drift | H25: India | I25: R&C | L25: 2 | M25: 8 | P25: 16 | Q25: 20 | R25: 24 | S25: 24 | V25: =SUM(J25:U25) -> 94
F26: API Layer & Microservices Implementation | H26: India | I26: R&C | M26: 6 | P26: 16 | Q26: 20 | R26: 32 | S26: 32 | V26: =SUM(J26:U26) -> 106
F27: Frontend Design & Agent Console / Trace Viewer | H27: India | I27: R&C | M27: 8 | P27: 20 | Q27: 28 | R27: 40 | S27: 40 | V27: =SUM(J27:U27) -> 136
F28: FE & BE Integration | H28: India | I28: R&C | M28: 6 | P28: 16 | Q28: 20 | R28: 24 | S28: 24 | V28: =SUM(J28:U28) -> 90
F29: Auth, RBAC, NFR & Enterprise Security Implementation | H29: India | I29: R&C | M29: 6 | P29: 16 | Q29: 20 | R29: 24 | S29: 24 | V29: =SUM(J29:U29) -> 90
F30: Component Testing, Red-Teaming & SIT | H30: India | I30: R&C | L30: 4 | M30: 10 | P30: 20 | Q30: 28 | R30: 36 | S30: 36 | V30: =SUM(J30:U30) -> 134
F31: User Acceptance Testing (incl. Bug Fixing) | H31: India | I31: R&C | L31: 1 | M31: 6 | P31: 12 | Q31: 20 | R31: 28 | S31: 28 | V31: =SUM(J31:U31) -> 95
F32: Documentation (Architecture, Agent Cards, AI Governance) | H32: India | I32: R&C | M32: 4 | P32: 12 | Q32: 16 | R32: 20 | S32: 20 | V32: =SUM(J32:U32) -> 72
F33: PMO & Programme Governance | H33: India | I33: R&C | N33: 140 | V33: =SUM(J33:U33) -> 140
F34: Go-live & Hypercare Support | H34: India | I34: R&C | M34: 4 | P34: 12 | Q34: 16 | R34: 16 | S34: 16 | V34: =SUM(J34:U34) -> 64
F35: Handover & Knowledge Transfer | H35: India | I35: R&C | J35: 1 | L35: 4 | M35: 4 | P35: 8 | Q35: 12 | R35: 12 | S35: 12 | V35: =SUM(J35:U35) -> 53
F36: Total | J36: =SUM(J8:J35) -> 5 | K36: =SUM(K8:K35) -> 0 | L36: =SUM(L8:L35) -> 85 | M36: =SUM(M8:M35) -> 238 | N36: =SUM(N8:N35) -> 140 | O36: =SUM(O8:O35) -> 0 | P36: =SUM(P8:P35) -> 472 | Q36: =SUM(Q8:Q35) -> 596 | ... V36: =SUM(V8:V35) -> 3168
H38: Project Mix | J38: =IFERROR(J36/$V$36,0) -> 0.0015782828 | K38: =IFERROR(K36/$V$36,0) -> 0 | L38: =IFERROR(L36/$V$36,0) -> 0.026830808 | M38: =IFERROR(M36/$V$36,0) -> 0.075126263 | N38: =IFERROR(N36/$V$36,0) -> 0.044191919 | O38: =IFERROR(O36/$V$36,0) -> 0 | P38: =IFERROR(P36/$V$36,0) -> 0.1489899 | Q38: =IFERROR(Q36/$V$36,0) -> 0.18813131 | ... U38: =IFERROR(U36/$V$36,0) -> 0
A41: F E E B R E A K D O W N | H41: =" All Values in ( "&C7&" )" -> All Values in ( INR ) | L41: What if analysis - FYI Only
A42: Total Engagement Value | D42: 8750000 | E42: Expenses Budgeting | L42: Pricing Tool - Home Office | Q42: Fee Amount | S42: Recovery %
A43: Description | D43: Org./ Name | F43: Hours Breakdown | G43: Fee Breakdown | H43: Budgeted Outlays | L43: Standard Fee | Q43: =$AB$5 -> 21105590 | S43: =$AB$5 -> 21105590
A44: Home Office | D44: =C4 -> India - R&C | F44: =V36 -> 3168 | G44: =D42-(SUM(G45:G48)+H49) -> 8750000 | H44: 0 | L44: ="Proposed Fee (Home Office)"&" - "&IF(D44=0,"",D44) -> Proposed Fee (Home Office) - India - R&C | Q44: =G44 -> 8750000 | S44: =S43*S47 -> 8750000
A45: Sub-Contractor (3rd party) | F45: 0 | G45: 0 | H45: 0 | L45: Planned Fee Adjustment (PFA) | Q45: =Q43-Q44 -> 12355590 | S45: =S43-S44 -> 12355590
F46: 0 | G46: 0 | H46: 0 | L46: PFA % | Q46: =IFERROR(Q45/Q43,0) -> 0.58541789 | S46: =1-S47 -> 0.58541789
F47: 0 | G47: 0 | H47: 0 | L47: Recovery % | Q47: =1-Q46 -> 0.41458211 | S47: =F51 -> 0.41458211
A48: GST | F48: 0 | G48: 0 | H48: 0
A49: Total | F49: =SUM(F44:F48) -> 3168 | G49: =SUM(G44:G48) -> 8750000 | H49: =SUM(H44:H48) -> 0
C51: Budgeted Recovery % | F51: =IFERROR(G44/$AB$5,0) -> 0.41458211
L52: Gross Fee | N52: Net Fee | P52: Net CM | R52: Gross CM
L53: Fee | M53: Per/Hr | N53: Fee | O53: Per/Hr | P53: % | R53: % | T53: Margin | V53: Staff Cost
K54: =C7 -> INR | L54: =G49 -> 8750000 | M54: =IFERROR(L54/F49,0) -> 2761.9949 | N54: =G44 -> 8750000 | O54: =IFERROR(N54/V36,0) -> 2761.9949 | P54: =IFERROR((T54-(N54*5%))/N54,0) -> 0.32961783 | R54: =IFERROR((L54-V54-(G49-G44)-(N54*5%))/L54,0) -> 0.32961783 | T54: =IFERROR(N54-V54,0) -> 3321656 | V54: =IFERROR($AB$6,0) -> 5428344
D56: Data to be entered / editable | L56: Gross Contribution Margin is derived after considering direct staff cost, management fees, Sub-contractor cost and other direct cost. Net Contribution Margin is derived after considering direct staff cost, management fees and other direct cost.
D57: Calculated - do not overwrite

Sheet 9. ChatBot
A1: Protiviti Member Firm (India) | V1: Project Template 2023 Apr.23
A2: Project Template - Fixed Fee Inclusive Outlays
A4: Organisation: | C4: India - R&C | X4: < Summary | Z4: RATE ENGINE (auto)
A5: Client Legal Name: | C5: YES BANK Ltd. | F5: Resource Plan (Home Office) - Budgeted Hours by Task and Resource Category | Z5: Standard Revenue (INR) | AB5: =SUMPRODUCT(J28:U28,Ratesheet!$B$23:$M$23) -> 8575590
A6: Project Description: | C6: ChatBot for Policies, SOPs & Document Retrieval | F6: Task Name | H6: Business Unit | J6: MD | K6: SD | L6: DIR | M6: AD | N6: SR. MGR | O6: MGR | P6: DM | Q6: SR. CONS. | R6: CON3 | S6: CON2 | T6: CON1 | U6: ANLST. | V6: TOTAL | X6: Ratesheet | Z6: Standard Staff Cost (INR) | AB6: =SUMPRODUCT(J28:U28,Ratesheet!$B$24:$M$24) -> 2198736
A7: Billing Currency: | C7: INR | H7: Country | I7: Service line | Z7: Blended chargeout / hr | AB7: =IFERROR(AB5/V28,0) -> 6501.5845
A8: Project Type: | C8: Fixed Fee (Incl. Outlays) | F8: Requirement Gathering & Document Corpus Study | H8: India | I8: R&C | J8: 1 | L8: 6 | M8: 6 | P8: 12 | Q8: 12 | R8: 16 | S8: 16 | V8: =SUM(J8:U8) -> 69 | Z8: Blended cost / hr | AB8: =IFERROR(AB6/V28,0) -> 1666.9719
F9: Technical Architecture, Design & Planning (RAG) | H9: India | I9: R&C | J9: 1 | L9: 6 | M9: 8 | P9: 12 | Q9: 12 | R9: 12 | S9: 12 | V9: =SUM(J9:U9) -> 63
F10: Document Corpus Ingestion, Parsing & Chunking | H10: India | I10: R&C | L10: 2 | M10: 6 | P10: 16 | Q10: 20 | R10: 28 | S10: 28 | V10: =SUM(J10:U10) -> 100
F11: Embedding Pipeline & Vector Store Setup | H11: India | I11: R&C | L11: 2 | M11: 6 | P11: 12 | Q11: 16 | R11: 24 | S11: 24 | V11: =SUM(J11:U11) -> 84
F12: Retrieval, Re-ranking & Answer Synthesis | H12: India | I12: R&C | L12: 4 | M12: 8 | P12: 16 | Q12: 20 | R12: 28 | S12: 28 | V12: =SUM(J12:U12) -> 104
F13: Citation, Grounding & Hallucination Controls | H13: India | I13: R&C | L13: 2 | M13: 6 | P13: 12 | Q13: 16 | R13: 20 | S13: 20 | V13: =SUM(J13:U13) -> 76
F14: Role-Based Document ACL & Secure Information Delivery | H14: India | I14: R&C | L14: 2 | M14: 6 | P14: 12 | Q14: 16 | R14: 20 | S14: 20 | V14: =SUM(J14:U14) -> 76
F15: Conversational UI & Chat Console | H15: India | I15: R&C | M15: 6 | P15: 12 | Q15: 20 | R15: 24 | S15: 24 | V15: =SUM(J15:U15) -> 86
F16: FE & BE Integration | H16: India | I16: R&C | M16: 4 | P16: 8 | Q16: 12 | R16: 16 | S16: 16 | V16: =SUM(J16:U16) -> 56
F17: Summarisation & Audit Artefact Retrieval Features | H17: India | I17: R&C | M17: 4 | P17: 8 | Q17: 12 | R17: 20 | S17: 20 | V17: =SUM(J17:U17) -> 64
F18: API Layer & Integration with ALCM / Checklist | H18: India | I18: R&C | M18: 4 | P18: 8 | Q18: 12 | R18: 16 | S18: 16 | V18: =SUM(J18:U18) -> 56
F19: Guardrails, Prompt Injection Defence & PII Redaction | H19: India | I19: R&C | L19: 2 | M19: 6 | P19: 12 | Q19: 16 | R19: 20 | S19: 20 | V19: =SUM(J19:U19) -> 76
F20: Auth, RBAC, Audit Trail & NFR Implementation | H20: India | I20: R&C | M20: 4 | P20: 8 | Q20: 12 | R20: 16 | S20: 16 | V20: =SUM(J20:U20) -> 56
F21: Accuracy Evaluation & Response Quality Tuning | H21: India | I21: R&C | L21: 2 | M21: 6 | P21: 12 | Q21: 16 | R21: 20 | S21: 20 | V21: =SUM(J21:U21) -> 76
F22: Component Testing & SIT | H22: India | I22: R&C | L22: 1 | M22: 4 | P22: 8 | Q22: 16 | R22: 20 | S22: 20 | V22: =SUM(J22:U22) -> 69
F23: User Acceptance Testing (incl. Bug Fixing) | H23: India | I23: R&C | L23: 1 | M23: 4 | P23: 8 | Q23: 12 | R23: 16 | S23: 16 | V23: =SUM(J23:U23) -> 57
F24: Documentation (Technical, User) | H24: India | I24: R&C | M24: 2 | P24: 4 | Q24: 8 | R24: 12 | S24: 12 | V24: =SUM(J24:U24) -> 38
F25: PMO & Programme Governance | H25: India | I25: R&C | N25: 50 | V25: =SUM(J25:U25) -> 50
F26: Go-live & Hypercare Support | H26: India | I26: R&C | M26: 2 | P26: 4 | Q26: 8 | R26: 8 | S26: 8 | V26: =SUM(J26:U26) -> 30
F27: Handover & Knowledge Transfer | H27: India | I27: R&C | J27: 1 | L27: 2 | M27: 2 | P27: 4 | Q27: 8 | R27: 8 | S27: 8 | V27: =SUM(J27:U27) -> 33
F28: Total | J28: =SUM(J8:J27) -> 3 | K28: =SUM(K8:K27) -> 0 | L28: =SUM(L8:L27) -> 32 | M28: =SUM(M8:M27) -> 94 | N28: =SUM(N8:N27) -> 50 | O28: =SUM(O8:O27) -> 0 | P28: =SUM(P8:P27) -> 188 | Q28: =SUM(Q8:Q27) -> 264 | ... V28: =SUM(V8:V27) -> 1319
H30: Project Mix | J30: =IFERROR(J28/$V$28,0) -> 0.0022744503 | K30: =IFERROR(K28/$V$28,0) -> 0 | L30: =IFERROR(L28/$V$28,0) -> 0.024260804 | M30: =IFERROR(M28/$V$28,0) -> 0.071266111 | N30: =IFERROR(N28/$V$28,0) -> 0.037907506 | O30: =IFERROR(O28/$V$28,0) -> 0 | P30: =IFERROR(P28/$V$28,0) -> 0.14253222 | Q30: =IFERROR(Q28/$V$28,0) -> 0.20015163 | ... U30: =IFERROR(U28/$V$28,0) -> 0
A33: F E E B R E A K D O W N | H33: =" All Values in ( "&C7&" )" -> All Values in ( INR ) | L33: What if analysis - FYI Only
A34: Total Engagement Value | D34: 3250000 | E34: Expenses Budgeting | L34: Pricing Tool - Home Office | Q34: Fee Amount | S34: Recovery %
A35: Description | D35: Org./ Name | F35: Hours Breakdown | G35: Fee Breakdown | H35: Budgeted Outlays | L35: Standard Fee | Q35: =$AB$5 -> 8575590 | S35: =$AB$5 -> 8575590
A36: Home Office | D36: =C4 -> India - R&C | F36: =V28 -> 1319 | G36: =D34-(SUM(G37:G40)+H41) -> 3250000 | H36: 0 | L36: ="Proposed Fee (Home Office)"&" - "&IF(D36=0,"",D36) -> Proposed Fee (Home Office) - India - R&C | Q36: =G36 -> 3250000 | S36: =S35*S39 -> 3250000
A37: Sub-Contractor (3rd party) | F37: 0 | G37: 0 | H37: 0 | L37: Planned Fee Adjustment (PFA) | Q37: =Q35-Q36 -> 5325590 | S37: =S35-S36 -> 5325590
F38: 0 | G38: 0 | H38: 0 | L38: PFA % | Q38: =IFERROR(Q37/Q35,0) -> 0.62101733 | S38: =1-S39 -> 0.62101733
F39: 0 | G39: 0 | H39: 0 | L39: Recovery % | Q39: =1-Q38 -> 0.37898267 | S39: =F43 -> 0.37898267
A40: GST | F40: 0 | G40: 0 | H40: 0
A41: Total | F41: =SUM(F36:F40) -> 1319 | G41: =SUM(G36:G40) -> 3250000 | H41: =SUM(H36:H40) -> 0
C43: Budgeted Recovery % | F43: =IFERROR(G36/$AB$5,0) -> 0.37898267
L44: Gross Fee | N44: Net Fee | P44: Net CM | R44: Gross CM
L45: Fee | M45: Per/Hr | N45: Fee | O45: Per/Hr | P45: % | R45: % | T45: Margin | V45: Staff Cost
K46: =C7 -> INR | L46: =G41 -> 3250000 | M46: =IFERROR(L46/F41,0) -> 2463.9879 | N46: =G36 -> 3250000 | O46: =IFERROR(N46/V28,0) -> 2463.9879 | P46: =IFERROR((T46-(N46*5%))/N46,0) -> 0.27346585 | R46: =IFERROR((L46-V46-(G41-G36)-(N46*5%))/L46,0) -> 0.27346585 | T46: =IFERROR(N46-V46,0) -> 1051264 | V46: =IFERROR($AB$6,0) -> 2198736
D48: Data to be entered / editable | L48: Gross Contribution Margin is derived after considering direct staff cost, management fees, Sub-contractor cost and other direct cost. Net Contribution Margin is derived after considering direct staff cost, management fees and other direct cost.
D49: Calculated - do not overwrite
